Workbook

Sheet Detaillierte Ergebnisse
A1: id | B1: category | C1: difficulty | D1: user_input | E1: response | F1: reference | G1: retrieved_contexts | H1: retrieved_urls | I1: retrieved_content_types | J1: faithfulness | K1: context_recall | L1: context_precision | M1: semantic_similarity | N1: context_entity_recall | O1: answer_relevancy | P1: bert_f1 | Q1: bert_precision | R1: bert_recall | S1: RR_at5 | T1: hit_at5 | U1: latency | V1: prompt_tokens | W1: completion_tokens | X1: total_tokens | Y1: reranking_tokens | Z1: context_count | AA1: response_time_seconds
A2: 1 | B2: Allgemein | C2: medium | D2: Inwiefern würde ich als Student von einem Studium an der WiSo-Fakultät profitieren? | E2: Als Student von einem Studium an der WiSo-Fakultät profitieren Sie in verschiedenen Bereichen: 1. Multidisziplinäre Ausrichtung: Im Verlauf des Studiums können Sie je nach gewählter Studienrichtung vom Austausch und von der Verknüpfung verschiedener Fachbereiche innerhalb der WiSo-Fakultät profitieren. 2. Möglichkeit eines Auslandsstudiums: Die WiSo-Fakultät bietet Ihren Studierenden die Möglichkeit eines Auslandsstudiums innerhalb ihres weltweiten und exzellenten Netzwerks an Partneruniversitäten. Ein Auslandsemester bietet die Chance, den Horizont zu erweitern, interkulturelle Kompetenzen zu erwerben und die akademische Laufbahn zu bereichern. 3. Gezielte inhaltliche Schwerpunkte: Sie können gezielt inhaltliche Schwerpunkte setzen, was Ihnen ermöglicht, Ihre Interessen und Fähigkeiten zu stärken. 4. Abschließende Masterarbeit: Für die abschließende Masterarbeit inklusive ihrer Verteidigung sind 30 LP vorgesehen. Diese Vorteile können dazu beitragen, dass Sie als Student von einem Studium an der WiSo-Fakultät eine umfassende und vielseitige Ausbildung erhalten. | F2: Als Student profitierst du von einem theorie- und methodenorientierten Studienansatz, in dem Forschung und Lehre eng mit der Praxis verzahnt sind, sowie von der ausgeprägten Praxisnähe durch die langjährige Zusammenarbeit der WiSo-Fakultät mit Unternehmen und Lehrbeauftragten aus verschiedenen Berufsfeldern. | G2: ['s den Bereichen BWL, VWL und Sozialwissenschaften gewählt werden. Die Masterthesis bildet den letzten Bereich und umfas st 30 LP. --- Page 8 --- Gültig für Studierende der PO 2021 (Einschreibung ab WiSe 2021/22) BUSINESS ADMINISTRATION : ACCOUNTING AND TAXATION - MASTER OF SCIENCE 4 1.4 Study Abroad Option Die WiSo -Fakultät bietet Ihren Studierenden die Möglichkeit eines Auslandsstudiums innerhalb ihres weltweiten und exzellenten Netzwerks an Partneruniversitäten . Ein Auslandsemester bietet die Chance, den Horizont zu erweitern, interkulturelle Kompetenzen zu erwerben und die akademische Laufbahn zu bereichern. Die Optionen im Überblick: 1. Study Abroad Programme (STAP): o Ein etabliertes Programm, das einen einsemestrigen Austausch an einer der renommierten Partnerhochschu len ermöglicht. Im Rahmen von STAP ist eine ERASMUS -Förderung möglich, die finanzielle Unterstützung während des Auslandssemesters bietet. o Vorteile: Direkter Kontakt zu den Partneruniversitäten, Organisatorische Unterstützung durch die WiSo -Fakultät , Befre iung von Studiengebühren an der Gasthochschule. 2. WiSo@: Akademische Kurzprogramme für WiSo Studierende o Es gibt jährlich die Möglichkeit, an akademischen Kurzprogrammen im Ausland teilzunehmen und so während der Semesterferien weitere Credits zu erwerben . 3. Fakultätsübergreifende Kooperationen : o Darüber hinaus gibt es noch weitere Möglichkeiten für ein Auslandsstudium, die durch das Dezernat 9 – Internationales (D9) der Universität zu Köln', 'mir sicher, dass ich durch diese Fähigkeit in der Zukunft auch selbst wirtschaftliche Prozesse mitgestalten kann.\n\nzum Seitenanfang\n\n### B.Sc. VWL - Studienrichtung Economics, Politics, and Society\n\n## Ihre Vorteile auf einen Blick:\n\n- Multidisziplinäre Ausrichtung: Im Verlauf des Studiums profitieren Sie je nach gewählter Studienrichtung vom Austausch und von der Verknüpfung verschiedener Fachbereiche innerhalb der WiSo-Fakultät. In zwei der drei Studienrichtungen können Sie volkswirtschaftliche Fragen durch die Brille von Politikwissenschaft, Soziologie oder Betriebswirtschaftslehre betrachten.\n- Frühzeitige Spezialisierung: Der Bachelorstudiengang Volkswirtschaftslehre bietet neben der typischen Grundausbildung in Ökonomik bereits frühzeitig einen Wahlbereich mit den Themen Behavioural Economics, Ecological Economics, Economic History und International Economics. Weitere Studienfächer behandeln aktuelle Themen wie Klimawandel, Einkommensverteilung, Arbeitsmarktdiskriminierung, Medienmärkte oder Bankenkrisen.\n- Verlinkung mit Deutschlands einzigem wirtschaftswissenschaftlichen Exzellenz-Cluster mit volkswirtschaftlichem Schwerpunkt: Der Fachbereich Volkswirtschaftslehre ist gegenwärtig Teil des Exzellenz-Clusters ECONTribute, in dem die Wissenschaftler:innen des Fachbereichs sich verstärkt mit dem Bereich Märkte und Public Policy beschäftigen und dabei durch umfangreiche Forschungsförderungen unterstützt werden. Clustermitglieder bringen sich und ihre Themen auch in der Le', 'Wirtschaftsinformatik und Data Analysis gewählt werden. Die Masterth esis bildet den letzten Bereich und umfasst 30 LP. --- Page 7 --- Gültig für Studierende der PO 2021 (Einschreibung ab WiSe 2021/22) BUSINESS ANALYTICS & ECONOMETRICS - MASTER OF SCIENCE 3 1.4 Study Abroad Option Die WiSo -Fakultät bietet Ihren Studierenden die Möglichkeit eines Auslandsstudiums innerhalb ihres weltweiten und exzellenten Netzwerks an Partneruniversitäten . Ein Auslandsemester bietet die Chance, den Horizont zu erweitern, interkulturelle Kompetenzen zu erwerben und die akademische Laufbahn zu bereichern. Die Optionen im Überblick: 1. Study Abroad Programme (STAP): o Ein etabliertes Programm, das einen einsemestrigen Austausch an einer der renommierten Partnerhochschulen ermöglicht. Im Rahmen von STAP ist eine ERASMUS -Förderung möglich, die finanzielle Unterstützung während des Auslandssemesters bietet. o Vorteile: Direkter Kontakt zu den Partneruniversitäten, Organisatorische Unterstützung durch die WiSo -Fakultät , Befreiung von Studiengebühren an der Gasthochschule. 2. WiSo@: Akademische Kurzprogramme für WiSo Studierende o Es gibt jährlich die Möglichkeit, an akademischen Kurzprogrammen im Ausland teilzunehmen und so während der Semesterferien weitere Credits zu erwerben . 3. Fakultätsübergreifende Kooperationen : o Darüber hinaus gibt es noch weitere Möglichkeiten für ein Auslandsstudium, die durch das Dezernat 9 – Internationales (D9) der Universität zu Köln angeboten werden. Au ch das', 'den gezielte inhaltliche Schwerpunkte setzen. Für die abschließende Masterarbeit inklusive ihrer Verteidigung sind 30 LP vorgesehen. 1.4 Study Abroad Opt ion Die WiSo -Fakultät bietet Ihren Studierenden die Möglichkeit eines Auslandsstudiums inner- halb ihres weltweiten und exzellenten Netzwerks an Partneruniversitäten . Ein Auslandsemes- ter bietet die Chance, den Horizont zu erweitern, interkulturelle Kompetenzen zu erwerben und die akademische Laufbahn zu bereichern. Die Optionen im Überblick: 1. Study Abroad Programme (STAP): o Ein etabliertes Programm, das einen einsemestrigen Austausch an einer der re- nommierten Partnerhochschulen ermöglicht. Im Rahmen von STAP ist eine ERASMUS -Förderung möglich, die finanzielle Unterstützung während des Aus- landssemesters bietet. o Vorteile: Direkter Kontakt zu den Partneruniversitäten, Organisatorische Unterstüt- zung durch die WiSo -Fakultät , Befreiung von Studiengebühren a n der Gasthoch- schule. 2. WiSo@NYC: Exklusive Summer School in New York City o Es gibt jährlich die Möglichkeit, an der exklusiven Summer School in einer der größten Metropolen der Welt teilzunehmen und während der Semesterferien weitere Credits zu erwerben. --- Page 8 --- Gültig für Studierende der PO 2021 (Einschreibung ab WiSe 2021/22) ECONOMIC RESEARCH – MASTER OF SCIENCE 8 3. Fakultätsübergreifende Kooperationen : o Darüber hinaus gibt es noch weitere Möglichkeiten für ein Auslandsstudium, die durch das Dezernat 9 – Internationales (D9) der Universität z', 'gt die Bachelorarbeit (12 LP). --- Page 8 --- Gültig für Studierende der PO 2021 (Einschreibung ab WiSe 2021/22) MODULHANDBUCH – BETRIEBSWIRTSCHAFTSLEHRE – BACHELOR OF SCIENCE 8 1.4 Study Abroad Option Die WiSo -Fakultät bietet Ihren Studierenden die Möglichkeit eines Auslandsstudiums innerhalb ihres weltweiten und exzellenten Netzwerks an Partneruniversitäten . Ein Auslandsemester bietet die Chance, den Horizont zu erweitern, interkulturelle Kompetenzen zu erwerben und die akademische Laufbahn zu bereichern. Die Optionen im Überblick: 1. Study Abroad Programme (STAP): o Ein etabliertes Programm, das einen einsemestrigen Austausch an einer der renommierten Partnerhochschulen ermöglicht. Im Rahmen von STAP ist eine ERASMUS -Förderung möglich, die finanzielle Unterstützung während des Auslandssemesters bietet. o Vorteile: Direkter Kontakt zu den Partneruniversitäten, Organisatorische Unterstützung durch die WiSo -Fakultät , Befreiung von Studiengebühren an der Gasthochschule. 2. WiSo@ : Akademische Kurzprogramme für W iSo Studierende o Es gibt jährlich die Möglichkeit, an akademischen Kurzprogrammen im Ausland teilzunehmen und so während der Semesterferien weitere Credits zu erwerben. Bachelorarbeit 12 LP Schwerpunktbereich 30 LPErgänzungsbereich 18 LP Basis-und Aufbaubereich 108 LP Gesamtumfang: 180 LP = 6 Semester Regelstudienzeit Studium Integrale 12 LP --- Page 9 --- Gültig für Studierende der PO 2021 (Einschreibung ab WiSe 2021/22) MODULHANDBUCH – BETRIEBSWIRTSCHAFTSLEHRE'] | H2: ['file://D:/Uni-Köln/Masterarbeit/Software/uzk-masterarbeit/data/pdf_cache/__wiso.uni-koeln.de_sites_fakultaet_dokumente_downloads_Modulhandbuecher_Master_MHB_aktuelles_Studienjahr_m_mhb_po2021_ba_accounting.pdf', 'https://wiso.uni-koeln.de/de/studium/bachelor/bachelor-vwl', 'file://D:/Uni-Köln/Masterarbeit/Software/uzk-masterarbeit/data/pdf_cache/__wiso.uni-koeln.de_sites_fakultaet_dokumente_downloads_Modulhandbuecher_Master_MHB_aktuelles_Studienjahr_m_mhb_po2021_business_analytics.pdf', 'file://D:/Uni-Köln/Masterarbeit/Software/uzk-masterarbeit/data/pdf_cache/__wiso.uni-koeln.de_sites_fakultaet_dokumente_downloads_Modulhandbuecher_Master_MHB_aktuelles_Studienjahr_m_mhb_po2021_economic_res.pdf', 'file://D:/Uni-Köln/Masterarbeit/Software/uzk-masterarbeit/data/pdf_cache/__wiso.uni-koeln.de_sites_fakultaet_dokumente_downloads_Modulhandbuecher_Bachelor_MHB_aktuelles_Studienjahr_b_mhb_po2021_bwl.pdf'] | I2: ['pdf', 'html', 'pdf', 'pdf', 'pdf'] | J2: 0.76923077 | K2: 0 | L2: 0 | M2: 0.69978004 | N2: 0.11111111 | O2: 0.92927389 | P2: 0.13976763 | Q2: 0.03489098 | R2: 0.24489997 | S2: 0 | T2: 0 | U2: 25.882106 | V2: 2271 | W2: 329 | X2: 2600 | Y2: 0 | Z2: 5 | AA2: 25.882106
A3: 2 | B3: Allgemein | C3: easy | D3: Welche Kosten fallen für reguläre Studienprogramme der WiSo-Fakultät an? | E3: Die Kosten für reguläre Studienprogramme der WiSo-Fakultät an der Universität zu Köln variieren je nach Studiengang und Art des Studiums. Hier sind einige allgemeine Informationen: * Die Semesterbeiträge für das Wintersemester 2022/23 betragen 302,50 € pro Monat (entspricht 1.151,00 € pro Semester) für Studenten mit deutscher Staatsbürgerschaft. * Für internationale Studierende gelten höhere Beiträge: 322,50 € pro Monat (entspricht 1.291,00 € pro Semester). * Darüber hinaus fallen Gebühren für die Studiengebühr an, die je nach Studiengang zwischen 150,00 € und 300,00 € pro Semester liegen kann. * Es gibt auch weitere Kosten wie z.B. für Bücher, Materialien, Reisen zu Praktika oder Auslandssemester. Es ist ratsam, sich direkt bei der Universität zu informieren, um die aktuellsten Informationen über die Kosten für das gewünschte Studienprogramm zu erhalten. Quelle: [Universität zu Köln - Semesterbeiträge](https://www.uni-koeln.de/studium/finanzielles/semesterbeitraege.html) | F3: Für die regulären Studienprogramme fällt nur der halbjährliche Semesterbeitrag an, der bereits das Semesterticket für den öffentlichen Nahverkehr in ganz Nordrhein-Westfalen umfasst. | G3: ['kultät studiert werden?\n\nFolgenden Masterstudiengänge werden an der WiSo-Fakultät angeboten:\n\n- Business Administration (mit 5 verschiedenen Spezialisierungen)\n- International Management (CEMS MIM)\n- Business Analytics and Econometrics\n- Economics\n- Economic Research\n- Politikwissenschaft\n- Sociology: Social Research\n- Sociology: Social and Economic Psychology\n- Gesundheitsökonomie\n- Information Systems\n- Wirtschaftspädagogik (M.Ed.)\n\nBeim Masterstudiengang Politikwissenschaft handelt es sich um einen Master of Arts, beim Masterstudiengang Wirtschaftspädagogik mit zwei Ausrichtungen um einen Master of Education/Master of Science. Die anderen Masterstudiengänge sind Master of Science. Nähere Informationen zu den einzelnen Studiengängen Sie auf unseren Internetseiten.\n\n## 4. Wieviel kostet ein Studium an der Universität zu Köln?\n\nStudiengebühren gibt es an der Universität zu Köln nicht, dafür wird pro Semester ein Semesterbeitrag fällig. Im Semesterbeitrag enthalten ist u.a. das NRW-Semesterticket, mit dem Sie in ganz Nordrhein-Westfalen den öffentlichen Personennahverkehr nutzen können. Nicht enthalten sind hier Kosten zum Lebensunterhalt, Verpflegung in der Mensa oder Lernmaterialien. Eine Orientierung zu weiteren Kosten Sie u.a. hier.\n\n## 5. Was zeichnet das Studium an der Wiso Fakultät aus?\n\nEin Studium an der WiSo-Fakultät der Universität zu Köln stellt eine hervorragende Ausgangsbasis für Ihre weiteren professionellen und persönlichen Pläne dar. Mit ca. 9.000 Studierenden', 'Studiengänge an der WiSo-Fakultät\n\n# Master\n\nWir freuen uns über Ihr Interesse an unseren Masterstudiengängen!\n\nDie Wirtschafts- und Sozialwissenschaftliche Fakultät (kurz: WiSo-Fakultät) der Universität zu Köln zählt konstant zu den Spitzenfakultäten in Deutschland. Sie zeichnet sich durch eine starke Forschungsorientierung, internationale Möglichkeiten sowie enge Verbindungen zu Wirtschaft und Gesellschaft aus. Unsere Masterstudiengänge, die auf Englisch unterrichtet werden, vermitteln den Studierenden die Fähigkeiten, Perspektiven und Netzwerke, um ihre globale Zukunft aktiv zu gestalten und einen bedeutenden Beitrag zu leisten. Die WiSo-Masterprogramme bieten eine erstklassige Ausbildung ohne Studiengebühren und eröffnen zahlreiche berufliche Perspektiven.\n\nNeben dem in Deutschland exklusiv angebotenen Master of International Management (CEMS MIM) und 5 Doppelmaster-Programmen bietet die Fakultät 15 konsekutive Masterstudiengänge in Betriebswirtschaftslehre, Volkswirtschaftslehre und Sozialwissenschaften sowie den Executive MBA an.\n\nHaben Sie noch weitere Fragen? Dann schauen Sie mal in unsere Master-FAQs!\n\n## Master-Virtueller Infotag\n\nBitte HIER ANMELDEN, um am virtuellen Master-Infotag teilzunehmen. Nutzen Sie die Gelegenheit, mehr über die WiSo-Fakultät zu erfahren, die Studienprogramme zu erkunden und wertvolle Einblicke von Professor:innen, aktuellen Studierenden und Alumni zu gewinnen.\n\n## Inhaltsverzeichnis\n\n- Unsere Masterprogramme in der Übersicht\n- Masterstudie', "ter-Infotag teilzunehmen. Nutzen Sie die Gelegenheit, mehr über die WiSo-Fakultät zu erfahren, die Studienprogramme zu erkunden und wertvolle Einblicke von Professor:innen, aktuellen Studierenden und Alumni zu gewinnen.\n\n## Inhaltsverzeichnis\n\n- Unsere Masterprogramme in der Übersicht\n- Masterstudiengänge mit WiSo-Beteiligung\n- Weitere Master der PO 2015\n\n## Unsere Masterprogramme in der Übersicht\n\n## International Management (CEMS MIM)\n\n## Business Administration\n\n## Double Master's Programme in Business Administration\n\n## Business Analytics & Econometrics\n\n## Economics\n\n## Double Master's Programme in Economics\n\n## Economic Research\n\n## Gesundheitsökonomie\n\n## Double Master's Programme in Health Economics and Management\n\n## Information Systems\n\n## Political Science\n\n## Double Master's Programme in European Studies\n\n## Sociology\n\n## Double Master's Programme in Demography and Social Inequality\n\n## Wirtschaftspädagogik\n\nzum Seitenanfang\n\n## Masterstudiengänge mit WiSo-Beteiligung\n\nAn der WiSo-Fakultät werden Wahlpflichtfächer zu den folgenden Verbund-Master der Philosophischen Fakultät studiert:\n\n- Medienwissenschaft\n- Regionalstudien China\n- Regionalstudien Lateinamerika\n- Regionalstudien Ost- und Mitteleuropa\n\nWeitere Informationen zu diesen Studiengängen erhalten Sie auf den Seiten der Philosophischen Fakultät.\n\nAuch in den Masterstudiengängen\n\n- Mathematik und\n- Wirtschaftsmathematik\n\nder Mathemathisch-Naturwissenschaftlichen Fakultät kann ein Nebenfach an der WiSo-Fakult", 'en der WiSo-Fakultät sind Ihnen bei Unsicherheiten und Fragen gerne behilflich.\n\n## 3. Welche Veranstaltungen kann ich im Studium Integrale belegen und was ist dabei zu beachten?\n\nGrundsätzlich können Sie jedes Modul im Studium Integrale absolvieren, welches in diesem Bereich in Ihrem Studiengangbaum in KLIPS 2.0 aufgeführt und zur Belegung freigeschaltet ist. Bitte beachten Sie aber, dass WiSo-Module die auch als reguläre Module in einem anderen WiSo-Bachelorstudiengang gelehrt werden, zur Belegung nicht freigeschaltet sind. Die Belegung der Module im Studium Integrale erfolgt ebenfalls über KLIPS 2.0. Insgesamt müssen Sie mindestens 12 ECTS im Studium Integrale erbringen. Zusätzlich können auch fachpraktische Tätigkeiten berücksichtigt werden.\n\n## 4. Sind Zusatzleistungen im Bachelorstudium möglich?\n\nDas Erbringen von Zusatzleistungen ist im Rahmen eines Bachelorstudiums an der WiSo-Fakultät der Universität zu Köln nicht vorgesehen und nicht möglich. Bitte haben Sie Verständnis dafür, dass aus Kapazitätsgründen keine Ausnahmen für diese Regelung möglich sind. Ausnahme bietet der Bereich des Studium Integrale. Hier können Sie mehr als die vorgesehenen 12 ECTS erbringen, die auch auf Ihrem Trancript of Records aufgeführt werden.\n\n## Auslandssemester und Praktika\n\n## 1. Wann muss ich mich zu einem Auslandssemester bewerben?\n\nSie haben einerseits die Möglichkeit, über das Zentrum für Internationale Beziehungen (ZIB) der WiSo-Fakultät an eine Partnerhochschule ins Ausland zu geh', 'en. Eine Orientierung zu weiteren Kosten Sie u.a. hier.\n\n## 5. Was zeichnet das Studium an der Wiso Fakultät aus?\n\nEin Studium an der WiSo-Fakultät der Universität zu Köln stellt eine hervorragende Ausgangsbasis für Ihre weiteren professionellen und persönlichen Pläne dar. Mit ca. 9.000 Studierenden und einer Vielzahl an Professuren und wissenschaftlichen Mitarbeitern ist die Fakultät eine der wissenschaftlich renommiertesten Fakultäten für Wirtschafts- und Sozialwissenschaften in Europa.\n\nEntscheidende Rankings bewerten die Qualität von Forschung und Lehre an Hochschulen und der Fakultätsentwicklung anhand verschiedener Kriterien. Die WiSo-Fakultät freut sich, ihre Position in vielen renommierten Rankings behaupten und in einigen Fällen ausbauen zu können.\n\nDie Verbindung von Forschung und Lehre, Theorie und Praxis, Wirtschafts- und Sozialwissenschaften begründet unser Leitbild: „Today\'s ideas. Tomorrow\'s impact". Innerhalb Ihres Studiums erarbeiten Sie mit Hilfe moderner Analysemethoden und Modelle neue Lösungsansätze für relevante wirtschafts- und sozialwissenschaftliche Zukunftsfragen.\n\nKöln ist nicht nur als Studienort eine attraktive Stadt. Sie ist weit über den Karneval hinaus für ihre vielfältige Kulturszene bekannt und stellt zusammen mit dem Umland einen der bedeutendsten Wirtschaftsstandorte in Deutschland dar.\n\n## Wenn Sie schon mal studiert haben\n\n## 1. Kann ich an der WiSo-Fakultät ein Studium aufnehmen, wenn ich einen gleichwertigen Studiengang bzw. eine dort v'] | H3: ['https://wiso.uni-koeln.de/de/studium/studienorganisation/faq/allgemeine-fragen', 'https://wiso.uni-koeln.de/de/studium/master', 'https://wiso.uni-koeln.de/de/studium/master', 'https://wiso.uni-koeln.de/de/studium/studienorganisation/faq/bachelor/fragen-im-bachelorstudium', 'https://wiso.uni-koeln.de/de/studium/studienorganisation/faq/allgemeine-fragen'] | I3: ['html', 'html', 'html', 'html', 'html'] | J3: 0.27272727 | K3: 1 | L3: 1 | M3: 0.61430154 | N3: 0.25 | O3: 0 | P3: 0.05437525 | Q3: -0.15783621 | R3: 0.28049436 | S3: 0 | T3: 0 | U3: 14.811629 | V3: 2230 | W3: 314 | X3: 2544 | Y3: 0 | Z3: 5 | AA3: 14.811629
A4: 3 | B4: Allgemein | C4: medium | D4: Wie wird die Qualität der WiSo-Absolvent:innen in Rankings und durch Arbeitgebereinschätzungen beschrieben? | E4: Die WiSo-Absolvent:innen werden in Rankings und Arbeitgeberbewertungen als hochwertig und qualifiziert beschrieben. Die Universität zu Köln, insbesondere die WiSo-Fakultät, hat sich in verschiedenen Hochschulrankings positioniert und wird von Personalverantwortlichen deutscher Unternehmen als Top-Ausbildungsstätte für BWL, VWL und Wirtschaftsinformatik angesehen. Die Absolvent:innen der WiSo-Fakultät profitieren vom theorie- und methodenorientierten Ansatz, der sowohl Forschung als auch Lehre mit der Praxis vereint. Die Nähe zur Praxis zeigt sich in der Lehre durch die langjährige Erfahrung in der Zusammenarbeit mit Unternehmen und Lehrbeauftragten aus verschiedenen Berufsfeldern. Insgesamt wird die WiSo-Fakultät für ihre hohen Qualitätsstandards und die erfolgreiche Vorbereitung ihrer Absolvent:innen auf den Arbeitsmarkt gelobt. | F4: Die Qualität der WiSo-Absolvent:innen wird dadurch hervorgehoben, dass mehrere DAX40-Vorstände an der Universität zu Köln studiert haben, sie laut dem aktuellen Ranking des Wirtschaftsmagazins „Wirtschaftswoche“ bei der Einstellung durch Personaler bevorzugt werden und die Fakultät im „Careers Rank“ des Financial Times Masters in Management Ranking eine deutschlandweite Spitzenposition einnimmt. | G4: ['# Rankings: Top positioniert\n\nHochschulrankings spielen in der Positionierung der Hochschule im nationalen und internationalen Umfeld sowie als Informationsquelle für Studieninteressierte, Arbeitgeber:innen, Ministerien und andere Stakeholder:innen eine wichtige Rolle. Entscheidende Rankings bewerten die Qualität von Forschung und Lehre an Hochschulen und der Fakultätsentwicklung anhand verschiedener Kriterien. Die WiSo-Fakultät freut sich, ihre Position in vielen renommierten Rankings behaupten und in einigen Fällen ausbauen zu können.\n\n> Hohe Rankingpositionen sind ein wichtiges Qualitätsindiz der Forschung und Lehre an der WiSo-Fakultät. Unsere exzellenten Ergebnisse in namhaften Rankings unterstreichen die Wettbewerbsfähigkeit der WiSo-Fakultät im nationalen sowie internationalen Hochschulumfeld.\n\nIm aktuellen Global Ranking of Academic Subjects (GRAS, "Shanghai Ranking")\xa0belegt die Universität zu Köln in der nationalen Auswertung Platz 1 für\xa0 "Sociology".\n\nIm AIS research ranking im Bereich Wirtschaftsinformatik liegt die UzK auf Platz 1 in Deutschland und auf Platz 4 in Europa.\n\nAn keiner anderen deutschen Hochschule haben so viele der aktuellen Vorstände der 40 Dax Unternehmen studiert wie an der Universität zu Köln. Die meisten davon kommen aus der WiSo-Fakultät (11. DAX Vorstandsreport, Handelsblatt).\n\nDie WiSo-Fakultät belegt in der Rubrik "International course experience rank" des Financial Times Masters in Management Rankings Platz 1 in Deutschland (weltweit Platz', '# Rankings: Top positioniert\n\nHochschulrankings spielen in der Positionierung der Hochschule im nationalen und internationalen Umfeld sowie als Informationsquelle für Studieninteressierte, Arbeitgeber:innen, Ministerien und andere Stakeholder:innen eine wichtige Rolle. Entscheidende Rankings bewerten die Qualität von Forschung und Lehre an Hochschulen und der Fakultätsentwicklung anhand verschiedener Kriterien. Die WiSo-Fakultät freut sich, ihre Position in vielen renommierten Rankings behaupten und in einigen Fällen ausbauen zu können.\n\n> Hohe Rankingpositionen sind ein wichtiges Qualitätsindiz der Forschung und Lehre an der WiSo-Fakultät. Unsere exzellenten Ergebnisse in namhaften Rankings unterstreichen die Wettbewerbsfähigkeit der WiSo-Fakultät im nationalen sowie internationalen Hochschulumfeld.\n\nIm aktuellen Global Ranking of Academic Subjects (GRAS, "Shanghai Ranking")\xa0belegt die Universität zu Köln in der nationalen Auswertung Platz 1 für\xa0 "Sociology".\n\nIm AIS research ranking im Bereich Wirtschaftsinformatik liegt die UzK auf Platz 1 in Deutschland und auf Platz 4 in Europa.\n\nAn keiner anderen deutschen Hochschule haben so viele der aktuellen Vorstände der 40 Dax Unternehmen studiert wie an der Universität zu Köln. Die meisten davon kommen aus der WiSo-Fakultät (11. DAX Vorstandsreport, Handelsblatt).\n\nDie WiSo-Fakultät belegt in der Rubrik "International course experience rank" des Financial Times Masters in Management Rankings Platz 1 in Deutschland (weltweit Platz', '# Rankings: Top positioniert\n\nHochschulrankings spielen in der Positionierung der Hochschule im nationalen und internationalen Umfeld sowie als Informationsquelle für Studieninteressierte, Arbeitgeber:innen, Ministerien und andere Stakeholder:innen eine wichtige Rolle. Entscheidende Rankings bewerten die Qualität von Forschung und Lehre an Hochschulen und der Fakultätsentwicklung anhand verschiedener Kriterien. Die WiSo-Fakultät freut sich, ihre Position in vielen renommierten Rankings behaupten und in einigen Fällen ausbauen zu können.\n\n> Hohe Rankingpositionen sind ein wichtiges Qualitätsindiz der Forschung und Lehre an der WiSo-Fakultät. Unsere exzellenten Ergebnisse in namhaften Rankings unterstreichen die Wettbewerbsfähigkeit der WiSo-Fakultät im nationalen sowie internationalen Hochschulumfeld.\n\nIm aktuellen Global Ranking of Academic Subjects (GRAS, "Shanghai Ranking")\xa0belegt die Universität zu Köln in der nationalen Auswertung Platz 1 für\xa0 "Sociology".\n\nIm AIS research ranking im Bereich Wirtschaftsinformatik liegt die UzK auf Platz 1 in Deutschland und auf Platz 4 in Europa.\n\nAn keiner anderen deutschen Hochschule haben so viele der aktuellen Vorstände der 40 Dax Unternehmen studiert wie an der Universität zu Köln. Die meisten davon kommen aus der WiSo-Fakultät (11. DAX Vorstandsreport, Handelsblatt).\n\nDie WiSo-Fakultät belegt in der Rubrik "International course experience rank" des Financial Times Masters in Management Rankings Platz 1 in Deutschland (weltweit Platz', '# Personaler-Ranking der Wirtschaftswoche 2020\n\n24.04.2020\n\nDie Universität zu Köln gehört auch 2020 zu den Top-Ausbildungsstätten für BWL, VWL und Wirtschaftsinformatik.\n\n"Von welcher dieser 200 Hochschule stellen Sie besonders gern Absolventen ein?" So lautet kurz gefasst die Kernfrage des jährlichen Personaler-Rankings der Wirtschaftswoche unter knapp 600 Personalverantwortlichen deutscher Unternehmen. Beim so zustande gekommenen Ranking belegt die WiSo-Fakultät 2020 erneut herausragende Platzierungen. Hinsichtlich der Berufschancen ihrer Absolventen ist die Universität zu Köln damit weiter eine Top-Adresse für ein BWL-, VWL- oder Wirtschaftsinformatik-Studium (nach denen unter anderem im Ranking differenziert wird).\n\nDies gilt dabei auch unter Einbezug der Bereiche, in denen private Hochschulen gute Rankingpositionen erzielen. So setzen die befragten Personalchef*Innen die WiSo-Fakultät etwa bei den BWL-Absolventen auf den 3 Platz. Im Bereich VWL, laut Wirtschaftswoche der „knappste“ Bereich des gesamten Rankings, liegt die WiSo-Fakultät auf dem 2. Rang und verbesserte sich damit um einen Platz gegenüber dem Vorjahr. Nicht zuletzt gehört die Universität zu Köln auch im Bereich Wirtschaftinformatik mit einem 6. Platz unter den gelisteten Universitäten und Fachhochschulen zu den Top Ten Ausbildungsstätten.\n\n• Informationen zum WiWo-Ranking\n\nZurück\n\n#### Social-Media-Kanäle der WiSo-Fakultät\n\n[ follow us! ]\n\nHI\n\nzum Seitenanfang', 'Studium an der WiSo-Fakultät\n\n# Starten Sie mit uns Ihren persönlichen Karriereweg!\n\nUnsere Studierenden profitieren in unseren Bachelor- und Masterstudiengängen vom theorie- und methodenorientierten Ansatz, der sowohl Forschung als auch Lehre mit der Praxis vereint. Die Nähe zur Praxis zeigt sich in der Lehre durch unsere langjährige Erfahrung in der Zusammenarbeit mit Unternehmen und Lehrbeauftragten aus verschiedenen Berufsfeldern. Ein Großteil unserer Lehrbeauftragten sind Fach- und Führungskräfte, die über wichtige Praxiserfahrungen verfügen. Dadurch können branchenspezifische und aktuelle Lehrinhalte kompetent und praxisnah vermittelt werden. Die Praxisorientierung, und somit die Verzahnung zwischen Praxis und Theorie im Studium, wird somit sicherstellt und der Austausch zwischen Studierenden und Unternehmen gefördert.\n\n## Top im Ranking\n\nMehrere DAX40-Vorstände studierten an der Universität zu Köln, soviele wie von keiner ansderen Universität. Dies unterstreicht die Fach- und Führungskompetenzen unserer Absolventen. Laut aktuellem Ranking des Wirtschaftsmagazins „Wirtschaftswoche“ werden unsere Absolventen bei der Einstellung durch Personaler bevorzugt. Eine deutschlandweite Spitzenposition halten wir derzeit in der Rubrik „Careers Rank“ des Financial Times Masters in Management Ranking. Hierbei wird betrachtet, wie viele der Absolventen drei Jahre nach Studienabschluss Führungspositionen verantworten und wie groß das jeweilige Unternehmen ist.\n\n## Internationale Ausri'] | H4: ['https://wiso.uni-koeln.de/de/service/rankings/', 'https://wiso.uni-koeln.de/de/services/rankings', 'https://wiso.uni-koeln.de/de/service/rankings', 'https://wiso.uni-koeln.de/de/aktuelles-und-neuigkeiten/news-einzelansicht/personaler-ranking-der-wirtschaftswoche-2020', 'https://wiso.uni-koeln.de/de/studium/bewerbung/studium-an-der-wiso-fakultaet'] | I4: ['html', 'html', 'html', 'html', 'html'] | J4: 1 | K4: 1 | L4: 0.36666667 | M4: 0.81694685 | N4: 0.625 | O4: 0.8201472 | P4: 0.18233339 | Q4: 0.12567064 | R4: 0.23648198 | S4: 0.2 | T4: 1 | U4: 13.043421 | V4: 2211 | W4: 258 | X4: 2469 | Y4: 0 | Z4: 5 | AA4: 13.043421
A5: 4 | B5: Allgemein | C5: medium | D5: Wie ist die internationale Ausrichtung der WiSo-Fakultät beschrieben? | E5: Die internationale Ausrichtung der WiSo-Fakultät der Universität zu Köln ist stark ausgeprägt. Die Fakultät bietet eine Vielzahl von Möglichkeiten, um internationale Erfahrungen zu sammeln, wie zum Beispiel das Optionale Auslandssemester oder die Teilnahme an Kurzprogrammen wie WiSo@NYC oder einer Summer School im Ausland. Die Fakultät ist Mitglied in mehreren Netzwerken internationaler Universitäten und bietet Kooperationen mit renommierten Partnerhochschulen weltweit, darunter Erasmus-Abkommen mit europäischen Universitäten. Dies ermöglicht es den Studierenden, ein Semester an einer internationalen Hochschule zu verbringen. Darüber hinaus bietet die WiSo-Fakultät eine breite BWL-Grundlagenausbildung und gleichzeitig die Möglichkeit einer individuellen Spezialisierung über vielfältige Angebote im Ergänzungs- und Schwerpunktbereich. Die Studierenden können ihre Kenntnisse und Fähigkeiten in anwendungsorientierten Modulen umsetzen, indem sie analytisches Denken und Handeln in die Praxis einbringen. Die internationale Ausrichtung der WiSo-Fakultät macht sie zu einem erstklassigen Ziel für Studierende, die eine Karriere in internationalen Arbeitsumgebungen anstreben. | F5: Die WiSo-Fakultät ist einziges deutsches Mitglied im CEMS-Netzwerk und bietet gemeinsam mit Partnern den Master in International Management (CEMS MIM) an. Viele Studienprogramme enthalten einen hohen Anteil englischsprachiger Module und nahezu alle Masterprogramme können vollständig auf Englisch studiert werden. Zudem bestehen Partnerschaften mit über 130 Hochschulen für Auslandssemester. | G5: ['sgewogenen Theorie- und Praxisansatz auf eine Karriere in internationalen Arbeitsumgebungen vor und befähigt Sie, in internationalisierten Unternehmen zu arbeiten.\n\nDarüber hinaus verfügt die WiSo-Fakultät über ein starkes Alumni-Netzwerk ehemaliger Studierender, die in allen Geschäftsbereichen weltweit tätig sind.\n\n### Eine internationale Fakultät\n\nDie internationale Ausrichtung und exzellente Reputation der WiSo-Fakultät der Universität zu Köln machen sie zu einem erstklassigen Ziel für Ihr Studium in Deutschland – mitten in Europa.\n\n- Veranstaltungskalender für internationale Studierende\n- Interesse an einem Deutschkurs? Fach- und Fertigkeitsspezifische Deutschkurse\n- Fragen zu Visum, Bescheinigungen oder Jobs? Das International Office hilft weiter!\n\nzum Seitenanfang\n\n## Karrieremöglichkeiten\n\nDieses Programm wird Sie für eine Karriere in einer Vielzahl von Rollen in verschiedenen Branchen qualifizieren. Nach Abschluss des Programms steigen unsere Studierenden in ein Management-Trainee-Programme, Stabsfunktionen in Strategie-, Unternehmensentwicklungs-, Compliance-Management-Einheiten oder Personalmanagement-Abteilungen ein. Viele starten ihre Karriere auch in Beratungsunternehmen. Potenzielle Arbeitgeber*innen reichen von Start-ups und kleinen/mittleren Unternehmen bis hin zu großen und globalen Konzernen.\n\nEbenso sind unsere Alumni branchenübergreifend und über alle Stufen der Wertschöpfungskette hinweg beschäftigt - von der Produktion über den Vertrieb bis hin zu Handel', 'h auf ein internationales und interkulturelles Umfeld an der Fakultät und auch innerhalb Ihres Studiengangs freuen können. Eine Vielzahl der Kurse wird je nach Spezialisierung in englischer Sprache angeboten.\n\n### Optionales Auslandssemester\n\nDie WiSo-Fakultät ist Mitglied in mehreren Netzwerken internationaler Universitäten, was Ihnen dabei hilft, ein Semester an einer renommierten Partnerhochschule im Ausland zu verbringen. Das Programm ist so konzipiert, dass Sie im vierten oder fünften Semester ein Auslandssemester absolvieren können. Wir beraten Sie gerne über Ihre Möglichkeiten und unterstützen Sie organisatorisch vor, während und nach Ihrem Auslandsaufenthalt.\n\n### Ihre Chance für globales Networking\n\nDer Studiengang bereitet Sie mit seinem ausgewogenen Theorie- und Praxisansatz auf den Einstieg in international ausgerichtete Berufe vor und befähigt Sie, in einem internationalisierten Umfeld zu arbeiten. Darüber hinaus verfügt die WiSo-Fakultät über ein breites Alumni-Netzwerk ehemaliger Studierender, die in allen Geschäftsbereichen rund um den Globus tätig sind.\n\n### Eine internationale Fakultät\n\nDie internationale Ausrichtung und exzellente Reputation der WiSo-Fakultät der Universität zu Köln machen sie zu einem erstklassigen Ziel für Dein Studium in Deutschland – mitten in Europa.\n\n- Veranstaltungskalender für internationale Studierende\n- Interesse an einem Deutschkurs? Fach- und Fertigkeitsspezifische Deutschkurse\n- Fragen zu Visum, Bescheinigungen', 'le verfügbaren Möglichkeiten zu nutzen, um eigene internationale Erfahrungen zu sammeln. Kooperationen mit einer Vielzahl exzellenter Partnerhochschulen weltweit, darunter Erasmus-Abkommen mit einer Vielzahl von europäischen Universitäten, bieten Ihnen attraktive Möglichkeiten, Ihr Auslandssemester zu verbringen. Wir beraten Sie gerne über ihre Möglichkeiten. Studierende, die ihr Auslandssemester selbst organisieren möchten, können dies als Freemover tun.\n\nZusätzlich zu einem Auslandssemester können Sie Ihr Studium bereichern, indem Sie an einem unserer Kurzprogramme wie WiSo@NYC oder einer Summer School im Ausland teilnehmen, oder ein Auslandspraktikum mit finanzieller Unterstützung durch Erasmus absolvieren.\n\n### Breites internationales Netzwerk\n\nDer international ausgerichtete Masterstudiengang bereitet Sie mit seinem ausgewogenen Theorie- und Praxisansatz auf eine Karriere in internationalen Arbeitsumgebungen vor und befähigt Sie, in internationalisierten Unternehmen zu arbeiten.\n\nDarüber hinaus verfügt die WiSo-Fakultät über ein starkes Alumni-Netzwerk ehemaliger Studierender, die in vielen Geschäftsbereichen weltweit tätig sind.\n\n### Eine internationale Fakultät\n\nDie internationale Ausrichtung und exzellente Reputation der WiSo-Fakultät der Universität zu Köln machen sie zu einem erstklassigen Ziel für Ihr Studium in Deutschland – mitten in Europa.\n\n- Veranstaltungskalender für internationale Studierende\n- Interesse an einem Deutschkurs? Fach- und Fertigkeitsspezifische', 'onnen, die in der weiteren beruflichen Laufbahn intensiviert und spezialisiert werden können.\n\n> Das Bachelorstudium der Betriebswirtschaftslehre an der Kölner WiSo-Fakultät bietet eine breite BWL-Grundlagenausbildung und gleichzeitig die Möglichkeit einer individuellen Spezialisierung über vielfältige Angebote im Ergänzungs- und Schwerpunktbereich. In anwendungsorientierten Modulen können Sie analytisches Denken und Handeln in die Praxis umsetzen, indem Sie die erworbenen Kenntnisse und Fähigkeiten zur Lösung praktischer Problemstellungen einsetzen.\n\nzum Seitenanfang\n\n## Akademische Exzellenz mit internationalem Angebot\n\n### Internationale Ausrichtung über das gesamte Studium hinweg\n\nFür den Großteil unseres Studienangebots erhalten wir Bewerbungen von einer großen Anzahl verschiedener Nationalitäten, sodass Sie sich auf ein internationales und interkulturelles Umfeld an der Fakultät und auch innerhalb Ihres Studiengangs freuen können. Eine Vielzahl der Kurse wird je nach Spezialisierung in englischer Sprache angeboten.\n\n### Optionales Auslandssemester\n\nDie WiSo-Fakultät ist Mitglied in mehreren Netzwerken internationaler Universitäten, was Ihnen dabei hilft, ein Semester an einer der über 140 renommierten Partnerhochschulen im Ausland zu verbringen. Das Programm ist so konzipiert, dass Sie im vierten oder fünften Semester ein Auslandssemester absolvieren können. Wir beraten Sie gerne über Ihre Möglichkeiten und unterstützen Sie organisatorisch vor, während und nach Ihrem Au', 'ter zu verbringen.\xa0Wir beraten Sie gerne über ihre Möglichkeiten. Studierende, die ihr Auslandssemester selbst organisieren möchten, können dies als Freemover tun. Zusätzlich zu einem Auslandssemester können Sie Ihr Studium bereichern, indem Sie an einem unserer Kurzprogramme wie WiSo@NYC oder einer Summer School im Ausland teilnehmen, oder ein Auslandspraktikum mit finanzieller Unterstützung durch Erasmus absolvieren.\n\n### Breites internationales Netzwerk\n\nDer international ausgerichtete Masterstudiengang bereitet Sie mit seinem ausgewogenen Theorie- und Praxisansatz auf eine Karriere in internationalen Arbeitsumgebungen vor und befähigt Sie, in internationalisierten Unternehmen zu arbeiten. Darüber hinaus verfügt die WiSo-Fakultät über ein starkes Alumni-Netzwerk ehemaliger Studierender, die in allen Geschäftsbereichen weltweit tätig sind.\n\n### Eine internationale Fakultät\n\nDie internationale Ausrichtung und exzellente Reputation der WiSo-Fakultät der Universität zu Köln machen sie zu einem erstklassigen Ziel für Ihr Studium in Deutschland – mitten in Europa.\n\n- Veranstaltungskalender für internationale Studierende\n- Interesse an einem Deutschkurs? Fach- und Fertigkeitsspezifische Deutschkurse\n- Fragen zu Visum, Bescheinigungen oder Jobs? Das International Office hilft weiter!\n\nzum Seitenanfang\n\n## Karrieremöglichkeiten\n\nDer M.Sc. in SCM zielt auf die Ausbildung zukünftiger Führungskräfte und Gründer:innen, die branchenübergreifend u.a. in der Logistik- und Produktionsplanu'] | H5: ['https://wiso.uni-koeln.de/de/studium/master/master-business-administration/corporate-development', 'https://wiso.uni-koeln.de/de/studium/bachelor/bachelor-wirtschaftsinformatik', 'https://wiso.uni-koeln.de/de/studium/master/master-business-administration/accounting-and-taxation', 'https://wiso.uni-koeln.de/de/studium/bachelor/bachelor-bwl', 'https://wiso.uni-koeln.de/de/studium/master/master-business-administration/supply-chain-management'] | I5: ['html', 'html', 'html', 'html', 'html'] | J5: 1 | K5: 0.66666667 | L5: 0 | M5: 0.64766007 | N5: 0.14285714 | O5: 0.8366044 | P5: 0.18402644 | Q5: 0.086959876 | R5: 0.28091517 | S5: 0 | T5: 0 | U5: 14.956461 | V5: 2190 | W5: 331 | X5: 2521 | Y5: 0 | Z5: 5 | AA5: 14.956461
A6: 5 | B6: Allgemein | C6: easy | D6: Welches Ziel verfolgen die Lehrinnovationen an der WiSo-Fakultät? | E6: Die Lehrinnovationen an der WiSo-Fakultät verfolgen das Ziel, die Lehre zu verbessern und neue Wege für eine effektive Vermittlung von Wissen zu beschreiben. Dazu gehören: 1. **Forschungsorientierte Lehre**: Die Lehre soll realen Problemen widerspiegeln und wissenschaftliche Ansätze zur Lösung von Problemen in der Praxis anwenden. 2. **Verbesserung der Lehrqualität**: Durch innovative Ideen und Lehrkonzepte sollen die Studierenden besser auf die Herausforderungen der Zukunft vorbereitet werden. 3. **Förderung von Kreativität und Kritikdenken**: Die WiSo-Fakultät möchte, dass die Studierenden kritisch denken und Probleme kreativ lösen können. Die Lehrinnovationen zielen darauf ab, die Studierenden auf die Herausforderungen der Zukunft vorzubereiten und sie zu eigenständigen und innovativen Denkern auszubilden. | F6: Mit den Lehrinnovationen möchte die WiSo-Fakultät ihre Lehre weiterentwickeln, indem sie neue Formen und Ansätze im Unterricht ausprobiert, um die Qualität der Lehrveranstaltungen zu steigern. Die Projekte können dabei inhaltlich sehr unterschiedlich sein, solange sie einen klaren Bezug zur Lehre haben. | G6: ['# Lehrinnovationen\n\nFür eine Verbesserung der Lehre entwickelt die WiSo-Fakultät innovative Ideen und Lehrkonzepte, die neue Wege beschreiten und die Lehrqualität verbessern. Dabei sind der Vielfältigkeit der Ideen – bis auf den erforderlichen Bezug zur Lehre – bewusst keine Grenzen gesetzt. Eine Auswahl der aktuellen Projekte Sie im Folgenden beschrieben.\n\n"Durch den Schwerpunkt der WiSo-Fakultät auf Innovation und Zusammenarbeit habe ich gelernt, kritisch zu denken, Probleme kreativ zu lösen und in vielfältigen Teams zu arbeiten – Fähigkeiten, die meinen Berufseinstieg beschleunigt haben und mir immer noch jeden Tag zum Erfolg verhelfen."\n\nMaximilian vom Eyser\nSenior Digital Growth Strategist, Google\n\nOnline Vorlesung: „Einführung in die Betriebswirtschaftslehre"\n\n## Weitere Lehrinnovationen an der WiSo-Fakultät\n\n## E-PLUS: Crowdsourcing-basiertes, individuelles Lernen\n\nInitiiert wurde das Projekt von Prof. Dr. Detlef Schoder, Inhaber des Seminars für Wirtschaftsinformatik und Informationsmanagement und akademischer Programm-Direktor für Wirtschaftsinformatik. Es wird erstmalig im Wintersemester 2017/18 im Rahmen der Lehrveranstaltung „Basismodul Grundlagen der Wirtschaftsinformatik“ (für Betriebswirte) angewandt. Angelehnt an das Konzept des Crowdsourcing konzipieren Studierende als Lernende im laufenden Semester Aufgaben und Lösungen zum Vorlesungsmaterial und bewerten und korrigieren die Aufgaben und Lösungen gegenseitig (Peer Reviewing). Die Studierenden werden somit ak', '# WiSo Strategie 2030\n\nDer WiSo Fakultätsentwicklungsplan\n\n# Inhaltsverzeichnis\n\n- Unsere Strategie für die Zukunft\n- Unsere strategischen Ziele bis 2030\n\n- Forschung\n- Lehre\n- Transfer\n- Karriere\n- Governance\n- Administrative und professionelle Dienstleistungen\n- Interdisziplinarität und Querschnittsthemen\n\n- Unsere Top Ten Prioritäten bis 2030\n- Gemeinsam die Zukunft gestalten!\n\n## Unsere Strategie für die Zukunft\n\nDie WiSo-Fakultät der Universität zu Köln stellt sich den Herausforderungen einer zunehmend globalisierten, digitalen und auf Nachhaltigkeit ausgerichteten Welt. Mit dem Strategischen Entwicklungsplan WiSo 2030 setzen wir uns klare Ziele, um unsere Position als eine der führenden akademischen Institutionen in den Bereichen Management, Volkswirtschaftslehre und Sozialwissenschaften weiter auszubauen.\n\nWir verfolgen das Ziel, exzellente Forschung mit gesellschaftlicher Relevanz zu verbinden, unseren Studierenden eine praxisorientierte Ausbildung zu bieten und einen positiven Beitrag für Menschen, Organisationen, die Gesellschaft und den Planeten zu leisten.\n\n## Unsere strategischen Ziele bis 2030\n\n### Forschung\n\n- Förderung der Forschung zu großen gesellschaftlichen Herausforderungen durch Forschungskooperationen\n- Erhöhung der externen Finanzierung zur Unterstützung unserer Forschung\n- Ausbau der Doktorand:innenausbildung zur Steigerung der Forschungsqualität und -leistung\n\n### Lehre\n\n- Steigerung von Relevanz und Wettbewerbsfähigkeit durch ein attraktives Studien', '# WiSo Strategie 2030\n\nDer WiSo Fakultätsentwicklungsplan\n\n# Inhaltsverzeichnis\n\n- Unsere Strategie für die Zukunft\n- Unsere strategischen Ziele bis 2030\n\n- Forschung\n- Lehre\n- Transfer\n- Karriere\n- Governance\n- Administrative und professionelle Dienstleistungen\n- Interdisziplinarität und Querschnittsthemen\n\n- Unsere Top Ten Prioritäten bis 2030\n- Gemeinsam die Zukunft gestalten!\n\n## Unsere Strategie für die Zukunft\n\nDie WiSo-Fakultät der Universität zu Köln stellt sich den Herausforderungen einer zunehmend globalisierten, digitalen und auf Nachhaltigkeit ausgerichteten Welt. Mit dem Strategischen Entwicklungsplan WiSo 2030 setzen wir uns klare Ziele, um unsere Position als eine der führenden akademischen Institutionen in den Bereichen Management, Volkswirtschaftslehre und Sozialwissenschaften weiter auszubauen.\n\nWir verfolgen das Ziel, exzellente Forschung mit gesellschaftlicher Relevanz zu verbinden, unseren Studierenden eine praxisorientierte Ausbildung zu bieten und einen positiven Beitrag für Menschen, Organisationen, die Gesellschaft und den Planeten zu leisten.\n\n## Unsere strategischen Ziele bis 2030\n\n### Forschung\n\n- Förderung der Forschung zu großen gesellschaftlichen Herausforderungen durch Forschungskooperationen\n- Erhöhung der externen Finanzierung zur Unterstützung unserer Forschung\n- Ausbau der Doktorand:innenausbildung zur Steigerung der Forschungsqualität und -leistung\n\n### Lehre\n\n- Steigerung von Relevanz und Wettbewerbsfähigkeit durch ein attraktives Studien', '# Forschungsorientierte Lehre\n\nDie Lehre an der WiSo-Fakultät zeichnet sich durch ihre Fokussierung auf Forschung, Theorie und Methoden aus. Daher widmet sich die Lehre realen Problemen, die gegenwärtige wirtschaftliche und soziale Veränderungen widerspiegeln. Die Studierenden werden aufgefordert, wissenschaftliche Ansätze zur Lösung von Problemen in der Praxis anzuwenden und bei Interesse frühzeitig Kenntnisse in der aktiven Forschung zu entwickeln. Daher legt die WiSo-Fakultät den Schwerpunkt auf den Erwerb von Forschungskompetenzen und die Anwendung der Theorie im Rahmen des gewählten Studiengangs.\n\nDiese Forschungsorientierung zeigt sich in der Gestaltung und Abfolge der Bachelor-, Master- und Doktorandenprogramme. Alle Programme haben einen gemeinsamen Kern, der sich an dem Fakultätsmotto "Today’s ideas. Tomorrow’s impact." orientiert. Dies zeigt sich sowohl in der Kombination von forschungsorientierter Lehre als auch durch die Berücksichtigung aktueller gesellschaftlicher Fragestellungen.\n\nEin positiver Trend in den letzten Jahren war die Zunahme von interaktiven Kursformaten, forschungsorientiertem Lernen und speziellen Kurs- und Serviceangeboten. Darüber hinaus hilft der verstärkte Einsatz von Fallstudien als Lehr- und Lernmethode den Studierenden, Forschungsergebnisse in der Praxis anzuwenden und praktische Managementfähigkeiten wie die Arbeit in (internationalen und interdisziplinären) Teams anzuwenden.\n\nDes Weiteren ist die WiSo-Fakultät bestrebt, ihre Programminha', 'evised mission and vision. The SILOs are:WiSo’s graduates make a positive impact in the world by addressing current and future challenges and (1) apply subject-related knowledge , analytical methods, and research-based approaches, (2) work with an open mind in diverse teams to share knowledge and develop solutions, and (3) actively engage in the development of their profes-sional and social environments. T he SILOs address students’ analytical skills and subject- related knowledge but also, social and personal competences and are translated into the Intended Learning Outcomes on programme, module and course level. They ensure that teaching and learning processes of the School focus on educating responsible graduates who make a positive impact in the world by addressing current and future challenges. WiSo is committed to fostering our students’ autonomy, sense of responsibility, discretion, critical thinking and readiness to fulfil high expectations, both during their studies and in their professional lives. The School aims to stimulate a culture of active learning and research-orientation while assisting students in mastering their field of study. Education at the School is characterised by a strong orientation towards research, theory and methods, with students playing an active role in their learning. They are encouraged to understand their own responsibility to shape a successful learning experience. A further characteristic is teaching which draws on reallife problems ref'] | H6: ['https://wiso.uni-koeln.de/de/studium/lehrinnovationen', 'https://wiso.uni-koeln.de/de/fakultaet/fakultaetsstrategie', 'https://wiso.uni-koeln.de/de/fakultaet/fakultaetsstrategie/wiso-strategie-2030', 'https://wiso.uni-koeln.de/de/studium/forschungsorientierte-lehre', 'file://D:/Uni-Köln/Masterarbeit/Software/uzk-masterarbeit/data/pdf_cache/__wiso.uni-koeln.de_sites_fakultaet_dokumente_ethik_WiSo-PRME-SIP-2022-web.pdf'] | I6: ['html', 'html', 'html', 'html', 'pdf'] | J6: 0.64285714 | K6: 1 | L6: 1 | M6: 0.85735251 | N6: 0.99999999 | O6: 0.97501414 | P6: 0.29177096 | Q6: 0.15998346 | R6: 0.4268249 | S6: 1 | T6: 1 | U6: 12.850104 | V6: 2229 | W6: 262 | X6: 2491 | Y6: 0 | Z6: 5 | AA6: 12.850104
A7: 6 | B7: Allgemein | C7: medium | D7: Worum geht es beim Lehrprojekt E-PLUS? | E7: Das Lehrprojekt E-PLUS beinhaltet verschiedene Aspekte: 1. **Individualisierte E-Prüfungen**: Die Studierenden können theoretisch jederzeit eine Klausur ablegen, was zur Entzerrung der Klausurtermine beiträgt. 2. **Wissenschaftliche Taschenrechner**: Für die Prüfungen an der WiSo-Fakultät sind bestimmte wissenschaftliche Taschenrechner erlaubt, wie z.B. Casio- oder Texas-Instruments-Taschenrechner. 3. **E-Hausaufgaben mit sofortiger Rückmeldung**: Das Projekt zielt darauf ab, ein neues E-Learning-Tool für regelmäßige, freiwillige Hausaufgaben (e-homework assignments) zu entwickeln. Das Lehrprojekt E-PLUS soll die Digitalisierung und Wirtschaftsethik in den Unterrichtsbereichen der WiSo-Fakultät stärken. | F7: Beim Lehrprojekt E-PLUS entwickeln Studierende während des Semesters eigene Übungsaufgaben und Lösungsvorschläge zum Vorlesungsstoff, bewerten diese gegenseitig in einem Peer-Review-Verfahren über die E-Learning-Plattform ILIAS und erhalten individuelles Feedback. Dadurch entsteht ein individualisierter, aktiver Lernprozess mit einem großen Aufgabenpool, der sie beim Üben und beim Vertiefen der Inhalte unterstützt und so den Lernerfolg verbessert. | G7: ['nstand reflektieren und anpassen können. Zudem hat der/die Dozent/in die Möglichkeit, bei der Auswertung der eingereichten Aufgaben und der Lösungen der Probe-Klausuren Schwachstellen zu identifizieren, die dann im Rahmen der Präsenzveranstaltung erneut aufgegriffen und erklärt werden können.\xa0\xa0\n\nDie Klausuren werden als individualisierte E-Prüfungen angeboten, die von den Studierenden theoretisch jederzeit abgelegt werden können. Dieses trägt unter anderem zur Entzerrung der Klausurtermine bei und entlastet sowohl den operativen als auch administrativen Prüfungsbetrieb.\n\n## Individuelle E-Hausaufgaben mit sofortigem Feedback\n\nDurch dieses Projekt soll ein neues E-Learning Tool für regelmäßige, freiwillige Hausaufgaben (E-Hausaufgaben) entwickelt werden. Verantwortlicher dieses interdisziplinären Projekts ist Herr Prof. Dr. Jörg Breitung (Institut für Ökonometrie und Statistik), Projektkoordinator ist Dr. Christoph Scheicher (Institut für Ökonometrie und Statistik).\n\nZiel des Projekts ist es, eine aktive Lehr-Lern Kultur in großen Pflichtveranstaltungen mit quantitativen Inhalten einzuführen. Dies soll durch regelmäßiges individuelles und unmittelbares Feedback für Lernende und Lehrende sowie durch eine Förderung des kontinuierlichen Lernens der Studierenden erreicht werden und zu einer besseren Klausurvorbereitung, besseren Noten sowie geringeren Durchfall- und Abbruchquoten führen.\n\nDafür soll ein neues E-Learning-Tool für regelmäßige, freiwillige Hausaufgaben (E-Hausaufgabe', '# Calculators\n\n### Scientific calculators for the exams at the WiSo Faculty (Updated: 26.10.2023)\n\n\xa0\n\n1.\nAll pocket calculators that do not have a complete alphabet on the keyboard are permitted, e.g:\n\nBrand Type\n\nCasio\nfx 82 all variants\n\nfx 83 all variants\n\nfx-85 all variants\n\nfx-86 all variants\n\nfx-87 all variants\n\nfx-115 all variantsfx-300MS\n\nfx-350 all variantsfx-580 VN X\n\nfx 570 ES Plusfx-991 all variants\n\nfx-810DE CW\n\nTexas Instruments\nTI 30 and all variants (incl. pro)\n\nTI-30x and all variants (incl. pro)\n\nTI 31 all variants (incl. pro)\n\nTI-36X all variants (incl. pro)\n\nSharp\nSharp EL-W531H\n\nSharp EL-W506 WriteView\n\nSharp EL-W506X WriteView\n\nSharp, EL-W550XG\n\nGlobaltronics Modell D1-5\n\nGENIE 92 SC 92 SC\n\nCALCOOM IQ-S8X\n\nDeli 1700 science calculator\n\nOsalo OS-991ES PLUS II\n\n\xa0\n\n\xa0\n\n\xa0\n\n\xa0\n\n\xa0\n\n\xa0\n\n\xa0\n\n\xa0\n\n\xa0\n\n\xa0\n\n\xa0\n\n\xa0\n\n\xa0\n\n\xa0\n\n\xa0\n\n\xa0\n\n\xa0\n\n\xa0\n\n\xa0\n\n\xa0\n\n\xa0\n\n\xa0\n\n\xa0\n\n\xa0\n\n\xa0\n\n\xa0\n\n\xa0\n\n\xa0\n\n\xa0\n\n\xa0\n\n\xa0\n\n\xa0\n\n\xa0\n\n\xa0\n\nIn addition, they have been tested and approved despite being complete alphabets:\n\nMarke Typ\n\nCasio fx3600Pv\nfx3800P\nfx3900Pv\nfx5500L, LA\nfx6200G\nfx7400G, G Plus\n\nHewlett-Packard 332S II RPN Scientific\n35s\n\nSharp 9200\n9300\n\n\xa0\n\n\xa0\n\n\xa0\n\n\xa0\n\n\xa0\n\n\xa0\n\n\xa0\n\n\xa0\n\n\xa0\n\n\xa0\n\n\xa0\n\n\xa0\n\n\xa0\n\nFurthermore tested and authorised:\n\nMarke Typ\n\nSharp\nSharp EL 531 TG\n\nSharp EL 531 TH\n\nSharp EL W531 TG\n\nSharp EL W531 TH\n\nSharp EL W531 XG\n\nSharp EL W531 XH\n\nVinacal\n\n(under Casio license)\nVinacal 570ES PLUS II\n\n\xa0\n\n\xa0\n\n\xa0\n\n\xa0\n\n\xa0\n\n\xa0\n\n\xa0\n\n\xa0\n\n\xa0\n\n\xa0\n\n\xa0\n\n\xa0\n\n\xa0\n\nIn particular, the following are not authorised:\n\nMarke Typ\n\nTexas Instruments 60-series\n70', 'be taken by the students at any time. This evens out the exam schedule and eases the workload both in terms of the conducting and the administration of the examinations.\n\n## Individual e-homework assignments with immediate feedback\n\nThis interdisciplinary project aims to develop a new e-learning tool for regular, voluntary homework (e-homework assignments). The project manager is Prof. Dr. Jörg Breitung (Institute of Econometrics and Statistics), supported by project coordinator Dr. Christoph Scheicher (Institute of Econometrics and Statistics). With this tool, the students receive completely individually composed exercises with different numbers and functions, which they have to solve. The tool ensures that the assignments do not overlap and students cannot copy others’ answers. This approach requires the students to actively engage with the content of the course, thus contributing to better understanding and a continuous process of preparation for the exams.\n\nAfter submitting their e-homework assignments, the students receive direct and individual feedback on their current level of learning, which promotes self-assessment of their previous ability and, if necessary, indicates what further action is necessary.\n\nThe e-homework assignment tool also uses, if available, a bonus point system, which could have a positive effect on the mark for the final examination if the assignments are completed successfully. This increases student motivation and leads to lower fail and drop-out', '# Calculators\n\n### Scientific calculators for the exams at the WiSo Faculty (Updated: 26.10.2023)\n\n\xa0\n\n1.\nAll pocket calculators that do not have a complete alphabet on the keyboard are permitted, e.g:\n\nBrand Type\n\nCasio\nfx 82 all variants\n\nfx 83 all variants\n\nfx-85 all variants\n\nfx-86 all variants\n\nfx-87 all variants\n\nfx-115 all variantsfx-300MS\n\nfx-350 all variantsfx-580 VN X\n\nfx 570 ES Plusfx-991 all variants\n\nfx-810DE CW\n\nTexas Instruments\nTI 30 and all variants (incl. pro)\n\nTI-30x and all variants (incl. pro)\n\nTI 31 all variants (incl. pro)\n\nTI-36X all variants (incl. pro)\n\nSharp\nSharp EL-W531H\n\nSharp EL-W506 WriteView\n\nSharp EL-W506X WriteView\n\nSharp, EL-W550XG\n\nGlobaltronics Modell D1-5\n\nGENIE 92 SC 92 SC\n\nCALCOOM IQ-S8X\n\nDeli 1700 science calculator\n\nOsalo OS-991ES PLUS II\n\n\xa0\n\n\xa0\n\n\xa0\n\n\xa0\n\n\xa0\n\n\xa0\n\n\xa0\n\n\xa0\n\n\xa0\n\n\xa0\n\n\xa0\n\n\xa0\n\n\xa0\n\n\xa0\n\n\xa0\n\n\xa0\n\n\xa0\n\n\xa0\n\n\xa0\n\n\xa0\n\n\xa0\n\n\xa0\n\n\xa0\n\n\xa0\n\n\xa0\n\n\xa0\n\n\xa0\n\n\xa0\n\n\xa0\n\n\xa0\n\n\xa0\n\n\xa0\n\n\xa0\n\n\xa0\n\nIn addition, they have been tested and approved despite being complete alphabets:\n\nMarke Typ\n\nCasio fx3600Pv\nfx3800P\nfx3900Pv\nfx5500L, LA\nfx6200G\nfx7400G, G Plus\n\nHewlett-Packard 332S II RPN Scientific\n35s\n\nSharp 9200\n9300\n\n\xa0\n\n\xa0\n\n\xa0\n\n\xa0\n\n\xa0\n\n\xa0\n\n\xa0\n\n\xa0\n\n\xa0\n\n\xa0\n\n\xa0\n\n\xa0\n\n\xa0\n\nFurthermore tested and authorised:\n\nMarke Typ\n\nSharp\nSharp EL 531 TG\n\nSharp EL 531 TH\n\nSharp EL W531 TG\n\nSharp EL W531 TH\n\nSharp EL W531 XG\n\nSharp EL W531 XH\n\nVinacal\n\n(under Casio license)\nVinacal 570ES PLUS II\n\n\xa0\n\n\xa0\n\n\xa0\n\n\xa0\n\n\xa0\n\n\xa0\n\n\xa0\n\n\xa0\n\n\xa0\n\n\xa0\n\n\xa0\n\n\xa0\n\n\xa0\n\nIn particular, the following are not authorised:\n\nMarke Typ\n\nTexas Instruments 60-series\n70', 'ziehen sich die Auswirkungen der Digitalisierung und der Wirtschaftsethik durch alle Unterrichtsbereiche.\n\nFakultätsmitglieder sind beispielsweise Mitglieder des neu gegründeten und von der Bundesregierung finanzierten Exzellenzclusters ECONtribute, dem derzeit einzigen Exzellenzcluster in Wirtschaftswissenschaften und Management in der deutschen Exzellenzstrategie. Da der Großteil der Forschung empirischer Natur ist, ist die Zusammenarbeit mit Organisationen und Unternehmen für die Mitglieder der Abteilung selbstverständlich.\n\n> Ich unterrichte sehr gerne in unserem Masterstudiengang, weil er eine sehr engagierte Gruppe von aufgeschlossenen Studierenden anzieht, die neugierig sind zu lernen und ihr Wissen anzuwenden. Wir tun unser Bestes, um sie mit dem Wissen und den Fähigkeiten auszustatten, in ihren späteren Karrieren im Management erfolgreich zu sein.\n\n### Business Project\n\nEin Highlight des Curriculums ist ein Wirtschaftsprojekt, in dem Sie in enger Zusammenarbeit mit einem Unternehmensvertreter*in aktuelle betriebswirtschaftliche Themen bearbeiten. Sie haben dabei die Gelegenheit, Ihre erworbenen Kenntnisse und Fähigkeiten in Gruppen von etwa vier Studierenden in einem Unternehmen zu erbringen. Darüber hinaus haben die Studierenden die Möglichkeit, sich in modernen Methoden der "People Analytics" zur Analyse von Organisationsdaten schulen zu lassen und diese Methoden bei der Bearbeitung eigener datengetriebener Forschungsprojekte anzuwenden.\n\n### Praxisbezug\n\nEin star'] | H7: ['https://wiso.uni-koeln.de/de/studium/lehrinnovationen', 'https://wiso.uni-koeln.de/en/faculty/managing-board/examination-office/2015-2021-examination-regulations/information-about-examinations/aids/calculators', 'https://wiso.uni-koeln.de/en/studies/teaching-innovations', 'https://wiso.uni-koeln.de/en/faculty/managing-board/central-faculty-administration/examination-office/2015-2021-examination-regulations/information-about-examinations/aids/calculators', 'https://wiso.uni-koeln.de/de/studium/master/master-business-administration/corporate-development'] | I7: ['html', 'html', 'html', 'html', 'html'] | J7: 0.72727273 | K7: 0.5 | L7: 0 | M7: 0.67756096 | N7: 0 | O7: 0.93399993 | P7: 0.13047329 | Q7: 0.040692236 | R7: 0.21934305 | S7: 1 | T7: 1 | U7: 12.303277 | V7: 2183 | W7: 233 | X7: 2416 | Y7: 0 | Z7: 5 | AA7: 12.303277
A8: 7 | B8: Allgemein | C8: medium | D8: Wie wird E-PLUS organisiert? | E8: Entschuldigung, aber ich konnte keine relevanten Informationen zu E-PLUS finden. Wenn du möchtest, kann ich mich bei der Studienberatung erkundigen, um dir eine genaue Antwort geben zu können. | F8: E-PLUS wird vollständig über die E-Learning-Plattform ILIAS organisiert. Dort werden die von den Studierenden erstellten Aufgaben bereitgestellt, im Peer-Review-Verfahren gegenseitig bewertet und offene Fragen in einem eigenen Wiki geklärt. | G8: ['onometrics: Ergänzungsbereich Business Analytics & Econometrics Master of Science Business Administration - Supply Chain Management: Ergänzungsbereich Supply Chain Management Master of Science Business Administration - Marketing: Ergänzungsbereich Marketing Master of Science Business Administration - Finance: Ergänzungsbereich Finance Master of Science Information Systems: Ergänzungsbereich Information Systems Master of Science Business Administration - Accounting and Taxation: Ergänzungsbereich Accounting and Taxation Master of Science Business Administration - Corporate Development: Ergänzungsbereich Corporate Development 9 Modulbeauftragte/r --- Page 204 --- Gültig für Studierende der PO 2021 (Einschreibung ab WiSe 2021/22) INFORMATION SYSTEMS - MASTER OF SCIENCE 200 10 Sonstige Informationen Sprach e: kann in Englisch oder in einer beliebigen Sprache an der Gastuniversität angeboten werden. Dieses Modul kann an einer ausländischen Hochschule studiert werden. In diesem Fall gibt es ein standardisiertes Anerkennungsverfahren. Informationen über die Kur sanerkennung (Fristen und Verfahren) stellt das Anrechnungszentrum zur Verfügung (WiSo Anrechnungszentrum: https://www.anrechnungwiso.uni -koeln.de/). Dieses Modul kann auch im Rahmen einer von der WiSo -Fakultät organisierten Summer School besucht werden. I n diesem Fall muss die vorherige Prüfungsanmeldung entsprechend den Bestimmungen der WiSo-Fakultät durchgeführt werden. --- Page 205 --- Gültig für Studierende der PO 202', 'im Versandhandel am Beispiel der Quelle AG – Bedeutung und organisatorische Verankerung. In: E-Organisation. Strategische und organisatorische Herausforderungen des Internet, Hrsg. von Erich Frese und Harald Stöber, Wiesbaden 2002. Steiner, Dieter; Lang, Carsten: E-Procurement bei IBM – Ausschöpfung von Beschaffungsmarktpotenzialen durch Zentralisierung und Internet-Technologie. In: E-Organisation. Strategische und organisatorische Herausforderungen des Internet, Hrsg. von Erich Frese und Harald Stöber, Wiesbaden 2002. Suske, Wolfgang; Lehmann, Patrick; Bungarten, Michael: Elektronisch unterstütztes Wissensmanagement als Meilenstein auf dem Weg zur Knowledge based Company – Das Beispiel Siemens. In: E-Organisation. Strategische und organisatorische Herausforderungen des Internet, Hrsg. von Erich Frese und Harald Stöber, Wiesbaden 2002. Theuvsen, Ludwig: E-Business und Strategie – Neubewertung von Wettbewerbsvorteilen bei veränderten Branchenstrukturen. In: E-Organisation. Strategische und organisatorische Herausforderungen des Internet, Hrsg. von Erich Frese und Harald Stöber, Wiesbaden 2002. Vetter, Thomas; Graumann, Matthias: Internetbasiertes Lernen – Der Ansatz von SAP . In: E-Organisation. Strategische und organisatorische Herausforderungen des Internet, Hrsg. von Erich Frese und Harald Stöber, Wiesbaden 2002. Seminar für Allgemeine Betriebswirtschaftslehre, betriebswirt- schaftliche Planung und Logistik Direktor: Prof. Dr. Werner Delfmann Forschungsvorhaben Partitionier', '002 gestartete Folgeprojekt hat zum Ziel, die in der Wirtschaft vorhandenen Netzwerke der Kammern, Verbände und Ausbildungsleiter-Arbeits- gemeinschaften für die Verbesserung der Datenlage zur betrieblichen Qualifikationsentwicklung zu nutzen und durch systematische und umfassende Informationen zum Qualifikationsbedarf die Grundlagen für Ent- scheidungen in der Aus- und Weiterbildung zur adäquaten Weiterentwicklung des Berufsbildungssystems zu verbessern. (Voraussichtlicher) Abschlusstermin: Jan 2005 Fördernde Institutionen: Bundesministerium für Bildung und Forschung (BMBF) Für wen außerhalb der Forschung ist Ihre Forschung interessant: Bildungsträger, Prüfungsausschüsse der Kammern, Verbände, Gremien der Ordnungsarbeit Qualifikationsentwicklung e-Business – Qualifikationsentwicklung im internationalen Vergleich Bearbeiter: Dr. Norbert Bromberger, Dipl.-Hdl. Markus Theodor Eickhoff, Dr. Friedrich H. Esser, Dipl.-Hdl. Björn Hekman, Michael Hoffschroer, Nadine Hofstedde, Jessica Weigt Leiter: Dr. Friedbert H. Esser, Univ.-Prof. Dr. Martin Twardy Gegenstand des Forschungsprojektes ist die durch die zunehmende Einführung von Electronic Business resul- tierende Qualifikationsentwicklung in kaufmännischen Tätigkeitsfeldern im internationalen Vergleich. In ausge- wählten Ländern (Finnland, Irland, USA) werden branchenspezifische (IT und Handel) Entwicklungen der Qua- lifikationsanforderungen erfasst und durch die Analyse der Strategien, Methoden und Modelle zur Bedarfs- deckung der', 'o- rative Untersuchung über die Konstruktion eines Messinstru-mentes. In: Wirtschaftspsychologie, 5. Jahrgang (2003), Nr. 2, S. 23-48. Graumann, Matthias; Wellhöfer, Alexander: E-Insurance und die Organisation von Versicherungsunternehmen. In: WISU – das Wirtschaftsstudium, 31. Jahrgang (2002), S. 682-688. Kreissl, Karl-Heinz; Bungarten, Michael; Lehmann, Patrick: Einsatz des Internet zur Unterstützung einer Fokussierungsstrategie im Bankensektor – Das Beispiel der Dresdner Bank. In: E-Organisation. Strategische und organisatorische Herausforderungen des Internet, hrsg. von Erich Frese und Harald Stöber, Wiesbaden 2002. Lang, Carsten; Utikal, Hannes: Organisatorische Impulse durch Internet-Technologie und technologieinduzier- te Strategien. In: E-Organisation. Strategische und organisatorische Herausforderungen des Internet, Hrsg. von Erich Frese und Harald Stöber, Wiesbaden 2002. Michels, Thomas; Valcárcel, Sylvia: E-Learning im AXA Konzern: Bisherige Erfahrungen und Erkenntnisse für die Zukunft. In: E-Organisation. Strategische und organisatorische Herausforderungen des Internet, Hrsg. von Erich Frese und Harald Stöber, Wiesbaden 2002. Rolz, Gerhard; Schiller, Simone: E-Commerce im Versandhandel am Beispiel der Quelle AG – Bedeutung und organisatorische Verankerung. In: E-Organisation. Strategische und organisatorische Herausforderungen des Internet, Hrsg. von Erich Frese und Harald Stöber, Wiesbaden 2002. Steiner, Dieter; Lang, Carsten: E-Procurement bei IBM – Ausschöpfung', 'in maligen Prüfungs termin durch die Vorsitzende beziehungsweise den Vorsitzenden des Prüfungs ausschusses vor Veranstaltungsbeginn des jewe iligen Moduls per Aushang b ekannt zu geben. (4) 1Eine elektronische Klausur (eKlausur) ist eine Prüfung, die am Computer mittels eines Prüfungsprogramms durchgeführt wird und deren Erstellung, Durchführung und Auswertung insgesamt durch Informations - und K ommunikationstechnologien unterstützt werden. 2Eine eKlausur ist zulässig, wenn sie dazu geeignet ist nachzuweisen, dass die Prüfungskandidatin oder der Prüfungskandidat die Inhalte und Methoden des Moduls in den wesentlichen Zusammenhängen beherrscht und die erworbenen Kenntnisse und Fähigkeiten anwenden kann; falls erforderlich kann sie durch andere Prüfungsformen ergänzt werden. 3Den Prüfungskandidatinnen oder den Prüfungskandidaten wird vor der Prüfung ausreichend Gelegenheit gegeben, sich mit dem elekt ronischen Prüfungssystem vertraut zu machen. 4Die eKlausur ist in Anwesenheit einer fachlich sachkundigen Person durchzuführen, die über den Prüfungsverlauf eine Niederschrift anfertigt. 5In diese sind mindestens die Namen der Protokollführerin oder des Pr otokollführers und der Prüfungskandidatinnen oder Prüfungskandidaten, Beginn und Ende der Prüfung sowie eventuelle besondere Vorkommnisse aufzunehmen. 6Es muss sichergestellt sein, dass die elektronischen Daten eindeutig und dauerhaft den Prüfungskandidati nnen oder Prüfungskandidaten zugeordnet werden können. 7Den Prüfungskandi'] | H8: ['file://D:/Uni-Köln/Masterarbeit/Software/uzk-masterarbeit/data/pdf_cache/__wiso.uni-koeln.de_sites_fakultaet_dokumente_downloads_Modulhandbuecher_Studienjahr_22-23_MHB_PO2021_m_mhb_po2021_is.pdf', 'file://D:/Uni-Köln/Masterarbeit/Software/uzk-masterarbeit/data/pdf_cache/__wiso.uni-koeln.de_sites_fakultaet_dokumente_forschung_Forschungsbericht_forschungsbericht2002_wiso.pdf', 'file://D:/Uni-Köln/Masterarbeit/Software/uzk-masterarbeit/data/pdf_cache/__wiso.uni-koeln.de_sites_fakultaet_dokumente_forschung_Forschungsbericht_forschungsbericht2002_wiso.pdf', 'file://D:/Uni-Köln/Masterarbeit/Software/uzk-masterarbeit/data/pdf_cache/__wiso.uni-koeln.de_sites_fakultaet_dokumente_forschung_Forschungsbericht_forschungsbericht2002_wiso.pdf', 'file://D:/Uni-Köln/Masterarbeit/Software/uzk-masterarbeit/data/pdf_cache/__wiso.uni-koeln.de_sites_fakultaet_dokumente_PA_po_po_ba_winfo.pdf'] | I8: ['pdf', 'pdf', 'pdf', 'pdf', 'pdf'] | J8: 0 | K8: 0 | L8: 0 | M8: 0.54284911 | N8: 0 | O8: 0 | P8: 0.15379441 | Q8: 0.19772667 | R8: 0.10688771 | S8: 0 | T8: 0 | U8: 7.9136751 | V8: 2199 | W8: 73 | X8: 2272 | Y8: 0 | Z8: 5 | AA8: 7.9136751
A9: 8 | B9: Allgemein | C9: hard | D9: Welchen Vorteil bietet das Projekt E-PLUS? | E9: Das Projekt E-PLUS bietet mehrere Vorteile, darunter: 1. **Individualisierte Prüfungen**: Die Möglichkeit für Studierende, theoretisch jederzeit eine Klausur abzulegen, was zu einer Entzerrung der Klausurtermine und einer besseren Klausurvorbereitung führt. 2. **Automatisches Feedback**: Ein neues E-Learning-Tool bietet automatische Bewertungen und Kommentare individueller Lösungswege und Fehler, was die Studierenden bei ihrer Lernprozess unterstützt. 3. **Bonuspunkte**: Ein Bonuspunktensystem kann eingesetzt werden, das eine positive Auswirkung auf die Note für die finale Prüfung hat, wenn die Aufgaben erfolgreich abgeschlossen werden. 4. **Internationale Vernetzung**: Die Möglichkeit, mit Menschen aus verschiedenen Kulturen in Kontakt zu treten und internationale Erfahrungen zu sammeln. 5. **Zertifikat und weitere Vorteile**: Ein Projektzertifikat zur Anerkennung der Auslandserfahrung sowie mögliche Weitere Vorteile wie Global Village, DAAD-Stipendium und Workshops. Ich hoffe, diese Informationen helfen dir weiter! | F9: Das Projekt E-PLUS bietet den Vorteil, dass durch die von den Studierenden selbst eingebrachten, individuellen Aufgaben ein breit gefächerter Aufgabenpool entsteht, aus dem viele verschieden aufgebaute E-Probe-Klausuren zum intensiven Üben generiert werden können. Die Studierenden erhalten zu ihren Bearbeitungen direktes Feedback, können ihren Lernstand dadurch gezielt reflektieren und anpassen und Lehrende erkennen typische Schwachstellen, die sie in der Präsenzveranstaltung noch einmal aufgreifen. Gleichzeitig werden die eigentlichen Klausuren als individualisierte E-Prüfungen angeboten, die zeitlich sehr flexibel abgelegt werden können, sodass sich die Klausurtermine entzerren und der Prüfungsbetrieb organisatorisch wie administrativ entlastet wird. | G9: ['nstand reflektieren und anpassen können. Zudem hat der/die Dozent/in die Möglichkeit, bei der Auswertung der eingereichten Aufgaben und der Lösungen der Probe-Klausuren Schwachstellen zu identifizieren, die dann im Rahmen der Präsenzveranstaltung erneut aufgegriffen und erklärt werden können.\xa0\xa0\n\nDie Klausuren werden als individualisierte E-Prüfungen angeboten, die von den Studierenden theoretisch jederzeit abgelegt werden können. Dieses trägt unter anderem zur Entzerrung der Klausurtermine bei und entlastet sowohl den operativen als auch administrativen Prüfungsbetrieb.\n\n## Individuelle E-Hausaufgaben mit sofortigem Feedback\n\nDurch dieses Projekt soll ein neues E-Learning Tool für regelmäßige, freiwillige Hausaufgaben (E-Hausaufgaben) entwickelt werden. Verantwortlicher dieses interdisziplinären Projekts ist Herr Prof. Dr. Jörg Breitung (Institut für Ökonometrie und Statistik), Projektkoordinator ist Dr. Christoph Scheicher (Institut für Ökonometrie und Statistik).\n\nZiel des Projekts ist es, eine aktive Lehr-Lern Kultur in großen Pflichtveranstaltungen mit quantitativen Inhalten einzuführen. Dies soll durch regelmäßiges individuelles und unmittelbares Feedback für Lernende und Lehrende sowie durch eine Förderung des kontinuierlichen Lernens der Studierenden erreicht werden und zu einer besseren Klausurvorbereitung, besseren Noten sowie geringeren Durchfall- und Abbruchquoten führen.\n\nDafür soll ein neues E-Learning-Tool für regelmäßige, freiwillige Hausaufgaben (E-Hausaufgabe', 'ende sowie durch eine Förderung des kontinuierlichen Lernens der Studierenden erreicht werden und zu einer besseren Klausurvorbereitung, besseren Noten sowie geringeren Durchfall- und Abbruchquoten führen.\n\nDafür soll ein neues E-Learning-Tool für regelmäßige, freiwillige Hausaufgaben (E-Hausaufgaben) eingesetzt werden, welches die Studierenden mit individuell unterschiedlichen Aufgabenstellungen versorgt. Das automatische Feedback bewertet und kommentiert individuelle Lösungswege und Fehler der Studierenden. Das individuelle Feedback ermöglicht sowohl den Studierenden als auch den Lehrenden, den Lernstand während des Semesters jederzeit detailliert einschätzen zu können und angemessen darauf zu reagieren.\n\nIm Rahmen des Projekts soll das neue Fragetool administrativ und technisch dauerhaft an der Universität zu Köln eingeführt und ein Aufgabenpool programmiert werden, der langfristig in fünf großen zentralen Grundlagenveranstaltungen des Bachelorstudiums eingesetzt werden soll.\n\nBegleitet werden die E-Hausaufgaben durch ggf. eine Bonuspunktevergabe, die sich bei erfolgreicher Erledigung der E-Hausaufgaben positiv auf die Note der Abschlussprüfung auswirken kann. Dies steigert schlussendlich die Motivation der Studierenden und führt zu geringeren Durchfall- und Abbruchquoten.\n\nDas E-Hausaufgaben-Tool wird ab Wintersemester 2017/18 nach und nach in den Bachelorveranstaltungen "Basismodul Mathematik", "Basismodul Mikroökonomik", "Basismodul Statistik", "Aufbaumodul Statistik" u', 't further action is necessary.\n\nThe e-homework assignment tool also uses, if available, a bonus point system, which could have a positive effect on the mark for the final examination if the assignments are completed successfully. This increases student motivation and leads to lower fail and drop-out rates.\n\nThe e-homework assignment tool will be used by and by\xa0from winter semester 2017/18 on the following bachelor courses: "Basic Module Mathematics", "Basic Module Microeconomics", "Basic Module Statistics","Advanced Module Statistics" and "Basic Module Fundamentals of Economics". In the long term, the plan is to expand the project both within the Faculty and University-wide to take in other courses in which quantitative mathematical or statistical methods are applied.\n\n## AufbaU: Tasks in Business Administration classes\n\nThe aim of the project - led by Prof. Dr. Matthias Pilz, holder of the Chair for Business and Economic Education and Training - is to optimise application-oriented learning tasks on the mass bachelor degree programme in Business Administration and to expand lecturers’ task-construction skills.\nIn contrast to pure exercises, these learning tasks not only allow students to revise and practise what they have learned in the lectures, but also to develop new competencies, based on the application of the acquired knowledge to solve real problems.\n\nAs part of this project, the first step in the 2017 summer term was to analyse the existing learning tasks in selected', 'rend des Projekts\n● Stadtführung vor Ort, um das Umfeld kennenzulernen\n● Internationale Vernetzung mit Menschen aus verschiedenen Kulturen\n● Projektzertifikat zur Anerkennung deiner Auslandserfahrung\n● Weitere Vorteile wie Global Village, DAAD-Stipendium und Workshops\n\nBereit für deinen nächsten Schritt?\nStarte dein Abenteuer mit Global Volunteer und werde Teil einer Bewegung, die junge Menschen weltweit\nverbindet. Gemeinsam gestalten wir eine bessere Zukunft – Schritt für Schritt.\nJetzt bewerben: aiesec.de/freiwilligenprojekte\nFragen? Schreib uns unter koeln@aiesec.de oder auf Instagram unter @goglobalcologne und\n@jinnythegoat.\n\n## Der ISC präsentiert: Consulting-Workshop!\n\nWir laden dich zu einem einzigartigen Workshop mit FTI-Andersch, der führenden Beratung im Bereich Turnaround in Deutschland ein. FTI-Andersch ist spezialisiert auf die nachhaltige Bewältigung schwierigster Unternehmenssituationen und die Umsetzung komplexer Transformationsprozesse\n\nWann? 20. November 2025\nWo? Universität zu Köln\n\nHighlights des Events:\n17.00 Uhr: Start des Workshops mit Vorstellung des Teams\n17.30 Uhr: Interaktiver Vortrag mit Einblicken in verschiedene Projektbeispiele\n19.00 Uhr: Get-together beim Dinner\n\nBewirb dich bis zum 13.11.2025 mit deinem CV per Mail an info@investmentstrategyclub.de\n\nNutze die Chance, wertvolle Einblicke zu gewinnen und Kontakte zu Branchenexperten zu knüpfen. Wir freuen uns auf deine Teilnahme!\n\nEuer ISC\n\n\xa0\n\n## Kontakt\n\nWiSo Student Service Point\nE-Mail: wiso-', 'be taken by the students at any time. This evens out the exam schedule and eases the workload both in terms of the conducting and the administration of the examinations.\n\n## Individual e-homework assignments with immediate feedback\n\nThis interdisciplinary project aims to develop a new e-learning tool for regular, voluntary homework (e-homework assignments). The project manager is Prof. Dr. Jörg Breitung (Institute of Econometrics and Statistics), supported by project coordinator Dr. Christoph Scheicher (Institute of Econometrics and Statistics). With this tool, the students receive completely individually composed exercises with different numbers and functions, which they have to solve. The tool ensures that the assignments do not overlap and students cannot copy others’ answers. This approach requires the students to actively engage with the content of the course, thus contributing to better understanding and a continuous process of preparation for the exams.\n\nAfter submitting their e-homework assignments, the students receive direct and individual feedback on their current level of learning, which promotes self-assessment of their previous ability and, if necessary, indicates what further action is necessary.\n\nThe e-homework assignment tool also uses, if available, a bonus point system, which could have a positive effect on the mark for the final examination if the assignments are completed successfully. This increases student motivation and leads to lower fail and drop-out'] | H9: ['https://wiso.uni-koeln.de/de/studium/lehrinnovationen', 'https://wiso.uni-koeln.de/de/studium/lehrinnovationen', 'https://wiso.uni-koeln.de/en/studies/teaching-innovations', 'https://wiso.uni-koeln.de/de/services/infomails-und-newsletter/bachelor-infomail/infomail-12-november-2025', 'https://wiso.uni-koeln.de/en/studies/teaching-innovations'] | I9: ['html', 'html', 'html', 'html', 'html'] | J9: 0.64705882 | K9: 1 | L9: 0.86666667 | M9: 0.77903911 | N9: 0 | O9: 0.98983701 | P9: 0.15692262 | Q9: 0.1001348 | R9: 0.21109189 | S9: 1 | T9: 1 | U9: 17.757603 | V9: 2136 | W9: 293 | X9: 2429 | Y9: 0 | Z9: 5 | AA9: 17.757603
A10: 9 | B10: Modulhandbuch/PO | C10: easy | D10: Welche Art von Dokumenten finden Studierende allgemein bezüglich Modulhandbücher und Prüfungsordnungen? | E10: Studierende finden allgemein Modulhandbücher und Prüfungsordnungen im Internetportal der Universität zu Köln, unter "Modulhandbuch-Archiv" oder in den jeweiligen Fachbereichen. | F10: Hierfür gibt es zentrale Dokumente zur Orientierung und Organisation des Studiums. Diese umfassen Modulhandbücher der aktuellen Prüfungsordnung PO 2021 für alle Bachelor- und Masterprogramme sowie Verweise auf die zugehörigen Prüfungsordnungen und ein Modulhandbuch-Archiv für frühere Jahrgänge. | G10: ['im Modulhandbuch.\n\n- Prüfungsrelevante Informationen und Regelungen Sie in der Prüfungsordnung.\n\n## Studienorganisation\n\nStudieren erfordert ein hohes Maß an Selbstorganisation. Im Folgenden haben wir für Sie Links zu hilfreichen Informationen, relevanten Tools und Beratungsstellen zusammengestellt, damit Sie Ihr Studium gut vorbereitet und richtig informiert erfolgreich bewältigen können.\n\n## Erstsemester\n\n## Klausureinsichtnahmen\n\n## Lehrveranstaltungs- und Prüfungsmanagement: KLIPS\n\n## Bescheinigungen\n\n## Finanzierung\n\n## Auslandsaufenthalt\n\n## FAQ\n\n## Arbeits- und Lernplätze\n\n## Hochschulweite Dienste\n\nHI\n\nzum Seitenanfang', '# Modulhandbücher und Prüfungsordnung\n\nHier Sie die gültigen Modulhandbücher und Prüfungsordnungen des aktuell laufenden Studienjahres der Prüfungsordnung (PO) 2021. Im Modulhandbuch-Archiv Sie darüberhinaus die Modulhandbücher vergangener Studienjahre.\n\n## Bachelor PO 2021\n\n## Master PO 2021\n\n## Modulhandbuch-Archiv\n\nHI\n\nzum Seitenanfang', '. ........................... 6 1.6 Modules with Mid -Term Examinations ................................ ................................ .23 1.7 Modularity ................................ ................................ ................................ .......... 23 2 STUDY ADVICE ................................ ................................ ................................ ........ 26 2.1 Guidance for Students ................................ ................................ ........................ 26 2.2 Organising Studies ................................ ................................ ............................. 26 2.3 Examinations ................................ ................................ ................................ ......27 2.4 Academic Practice ................................ ................................ .............................. 28 3 MODULE TABLES AND DESCRIPTIONS ................................ ................................ .29 3.1 Core and Advanced Section ................................ ................................ ................ 29 3.2 Specialisation Section ................................ ................................ ......................... 30 3.3 Studium Integrale ................................ ................................ ............................... 33 3.4 Bachelor’s Thesis ................................ ................................ ............................... 34 3.5 Module Descriptions ....', '# Modulhandbücher und Prüfungsordnung\n\nHier Sie die gültigen Modulhandbücher und Prüfungsordnungen des aktuell laufenden Studienjahres der Prüfungsordnung (PO) 2021. Im Modulhandbuch-Archiv Sie darüberhinaus die Modulhandbücher vergangener Studienjahre.\n\n## Bachelor PO 2021\n\n## Master PO 2021\n\n## Modulhandbuch-Archiv\n\nHI\n\nzum Seitenanfang', '1.5 Studienverlaufsempfehlungen ................................ ................................ .................. 6 1.6 Midterm -Regelung ................................ ................................ ................................ ... 8 2 STUDIENHILFEN ................................ ................................ ................................ . 9 2.1 Erste Anlaufstelle für Beratung ................................ ................................ ................. 9 2.2 Studienorganisation ................................ ................................ ................................ 9 2.3 Prüfungen ................................ ................................ ................................ .............. 10 3 MODULTABELLEN UND MO DULBESCHREIBUNGEN ................................ .. 12 3.1 Basisbereich ................................ ................................ ................................ ........... 12 3.2 Schwerpunktbereich ................................ ................................ ............................... 12 3.3 Ergänzungsbereich ................................ ................................ ................................ .13 3.4 Extracurriculare Angebote ................................ ................................ ....................... 17 3.5 Masterarbeit ................................ ................................ ................................ ............ 18 3.6 Modulbeschreibungen ..................'] | H10: ['https://wiso.uni-koeln.de/de/studium/bachelor/bachelor-vwl/studienaufbau', 'https://wiso.uni-koeln.de/de/studium/modulhandbuecher-und-pruefungsordnungen?and=&cHash=0b87324d1375e4f2beb9036c79aa21db', 'file://D:/Uni-Köln/Masterarbeit/Software/uzk-masterarbeit/data/pdf_cache/__wiso.uni-koeln.de_sites_fakultaet_dokumente_downloads_Modulhandbuecher_Bachelor_MHB_aktuelles_Studienjahr_b_module_catalogue_economics_po2021.pdf', 'https://wiso.uni-koeln.de/de/studium/modulhandbuecher-und-pruefungsordnungen?Chain=&cHash=48741bdec96c2f016003263d312f4737', 'file://D:/Uni-Köln/Masterarbeit/Software/uzk-masterarbeit/data/pdf_cache/__wiso.uni-koeln.de_sites_fakultaet_dokumente_downloads_Modulhandbuecher_Master_MHB_aktuelles_Studienjahr_m_mhb_po2021_ba_marketing.pdf'] | I10: ['html', 'html', 'pdf', 'html', 'pdf'] | J10: 0 | K10: 1 | L10: 1 | M10: 0.64747708 | N10: 0.4 | O10: 0.6937629 | P10: 0.35634071 | Q10: 0.41598895 | R10: 0.29516256 | S10: 0 | T10: 0 | U10: 7.7362537 | V10: 2074 | W10: 88 | X10: 2162 | Y10: 0 | Z10: 5 | AA10: 7.7362537
A11: 10 | B11: Modulhandbuch/PO | C11: easy | D11: Für welche Studierendengruppe gelten die Dokumente im Rahmen der Bachelor PO 2021? | E11: Die Dokumente im Rahmen der Bachelor PO 2021 gelten für Studierende, die ab dem Wintersemester 2021/22 eingeschrieben sind. | F11: Die Dokumente sind gültig für Studierende der Prüfungsordnung 2021, die sich ab dem Wintersemester 2021/22 in einen entsprechenden Bachelorstudiengang eingeschrieben haben. | G11: ['der PO 2021 (Einschreibung ab WiSe 2021/22) MODULHANDBUCH - VOLKSWIRTSCHAFTSLEHRE - BACHELOR OF SCIENCE 13 --- Page 18 --- Gültig für Studierende der PO 2021 (Einschreibung ab WiSe 2021/22) MODULHANDBUCH - VOLKSWIRTSCHAFTSLEHRE - BACHELOR OF SCIENCE 14 --- Page 19 --- Gültig für Studierende der PO 2021 (Einschreibung ab WiSe 2021/22) MODULHANDBUCH - VOLKSWIRTSCHAFTSLEHRE - BACHELOR OF SCIENCE 15 --- Page 20 --- Gültig für Studierende der PO 2021 (Einschreibung ab WiSe 2021/22) MODULHANDBUCH - VOLKSWIRTSCHAFTSLEHRE - BACHELOR OF SCIENCE 16 Hinweis zum Wahlbereich VWL soz.: Falls der Master in Social and Economic Psychology angestrebt wird, sollte das Modul BM Einführung in die Psychologie ( 1320BBWPS1) spätestens im vorletzten Semester belegt werden. --- Page 21 --- Gültig für Studierende der PO 2021 (Einschreibung ab WiSe 2021/22) MODULHANDBUCH - VOLKSWIRTSCHAFTSLEHRE - BACHELOR OF SCIENCE 17 --- Page 22 --- Gültig für Studierende der PO 2021 (Einschreibung ab WiSe 2021/22) MODULHANDBUCH - VOLKSWIRTSCHAFTSLEHRE - BACHELOR OF SCIENCE 18 Hinweis zum Wahlbereich VWL soz.: Falls der Master in Social and Economic Psychology angestrebt wird, sollte das Modul BM Einführung in die Psychologie (1320BBWPS1) spätestens im vorletzten Semester belegt werden. --- Page 23 --- Gültig für Studierende der PO 2021 (Einschreibung ab WiSe 2021/22) MODULHANDBUCH - VOLKSWIRTSCHAFTSLEHRE - BACHELOR OF SCIENCE 19 --- Page 24 --- Gültig für Studierende der PO 2021 (Einschreibung ab WiSe 2021/22) MODUL', 'rende der PO 2021 (Einschreibung ab WiSe 2021/22) MODULHANDBUCH - VOLKSWIRTSCHAFTSLEHRE - BACHELOR OF SCIENCE 16 --- Page 21 --- Gültig für Studierende der PO 2021 (Einschreibung ab WiSe 2021/22) MODULHANDBUCH - VOLKSWIRTSCHAFTSLEHRE - BACHELOR OF SCIENCE 17 Hinweis zum Wahlbereich VWL soz.: Falls der Master in Social and Economic Psychology angestrebt wird, sollte das Modul BM Einführung in die Psychologie (1320BBWPS1) spätestens im vorletzten Semester belegt werden. --- Page 22 --- Gültig für Studierende der PO 2021 (Einschreibung ab WiSe 2021/22) MODULHANDBUCH - VOLKSWIRTSCHAFTSLEHRE - BACHELOR OF SCIENCE 18 --- Page 23 --- Gültig für Studierende der PO 2021 (Einschreibung ab WiSe 2021/22) MODULHANDBUCH - VOLKSWIRTSCHAFTSLEHRE - BACHELOR OF SCIENCE 19 Hinweis zum Wahlbereich VWL soz.: Falls der Master in Social and Economic Psychology angestrebt wird, sollte das Modul BM Einführung in die Psychologie (1320BBWPS1) spätestens im vorletzten Semester belegt werden. --- Page 24 --- Gültig für Studierende der PO 2021 (Einschreibung ab WiSe 2021/22) MODULHANDBUCH - VOLKSWIRTSCHAFTSLEHRE - BACHELOR OF SCIENCE 20 --- Page 25 --- Gültig für Studierende der PO 2021 (Einschreibung ab WiSe 2021/22) MODULHANDBUCH - VOLKSWIRTSCHAFTSLEHRE - BACHELOR OF SCIENCE 21 Hinweis zum Wahlbereich VWL soz. (1/2) : Falls der Master in Politikwissenschaft angestrebt wird, soll te das Modul SM Vertiefung Politikwissenschaft (1335BSVPW1) spätestens im vorletzten Semester belegt werden. Hinweis zum Wahlb', 'Semester ). --- Page 12 --- Gültig für Studierende der PO 2021 (Einschreibung ab WiSe 2021/22) MODULHANDBUCH - VOLKSWIRTSCHAFTSLEHRE - BACHELOR OF SCIENCE 8 Hinweis zum Wahlbereich VWL: Falls der Master in Social and Economic Psychology angestrebt wird, sollte das Modul BM Einführu ng in die Psychologie (1320BBWPS1) spätestens im vorletzten Semester belegt werden. --- Page 13 --- Gültig für Studierende der PO 2021 (Einschreibung ab WiSe 2021/22) MODULHANDBUCH - VOLKSWIRTSCHAFTSLEHRE - BACHELOR OF SCIENCE 9 --- Page 14 --- Gültig für Studierende der PO 2021 (Einschreibung ab WiSe 2021/22) MODULHANDBUCH - VOLKSWIRTSCHAFTSLEHRE - BACHELOR OF SCIENCE 10 Hinweis zum Wahlbereich VWL: Falls der Master in Social and Economic Psychology angestrebt wird, sollte das Modul BM Einführu ng in die Psychologie (1320BBWPS1) spätestens im vorletzten Semester belegt werden. --- Page 15 --- Gültig für Studierende der PO 2021 (Einschreibung ab WiSe 2021/22) MODULHANDBUCH - VOLKSWIRTSCHAFTSLEHRE - BACHELOR OF SCIENCE 11 --- Page 16 --- Gültig für Studierende der PO 2021 (Einschreibung ab WiSe 2021/22) MODULHANDBUCH - VOLKSWIRTSCHAFTSLEHRE - BACHELOR OF SCIENCE 12 --- Page 17 --- Gültig für Studierende der PO 2021 (Einschreibung ab WiSe 2021/22) MODULHANDBUCH - VOLKSWIRTSCHAFTSLEHRE - BACHELOR OF SCIENCE 13 --- Page 18 --- Gültig für Studierende der PO 2021 (Einschreibung ab WiSe 2021/22) MODULHANDBUCH - VOLKSWIRTSCHAFTSLEHRE - BACHELOR OF SCIENCE 14 --- Page 19 --- Gültig für Studierende der PO 2', 'in die Psychologie (1320BBWPS1) spätestens im vorletzten Semester belegt werden. --- Page 14 --- Gültig für Studierende der PO 2021 (Einschreibung ab WiSe 2021/22) MODULHANDBUCH - VOLKSWIRTSCHAFTSLEHRE - BACHELOR OF SCIENCE 10 --- Page 15 --- Gültig für Studierende der PO 2021 (Einschreibung ab WiSe 2021/22) MODULHANDBUCH - VOLKSWIRTSCHAFTSLEHRE - BACHELOR OF SCIENCE 11 Hinweis zum Wahlbereich VWL: Falls der Master in Social and Economic Psychology angestrebt wird, sollte das Modul BM Einführu ng in die Psychologie (1320BBWPS1) spätestens im vorletzten Semester belegt werden. --- Page 16 --- Gültig für Studierende der PO 2021 (Einschreibung ab WiSe 2021/22) MODULHANDBUCH - VOLKSWIRTSCHAFTSLEHRE - BACHELOR OF SCIENCE 12 --- Page 17 --- Gültig für Studierende der PO 2021 (Einschreibung ab WiSe 2021/22) MODULHANDBUCH - VOLKSWIRTSCHAFTSLEHRE - BACHELOR OF SCIENCE 13 --- Page 18 --- Gültig für Studierende der PO 2021 (Einschreibung ab WiSe 2021/22) MODULHANDBUCH - VOLKSWIRTSCHAFTSLEHRE - BACHELOR OF SCIENCE 14 --- Page 19 --- Gültig für Studierende der PO 2021 (Einschreibung ab WiSe 2021/22) MODULHANDBUCH - VOLKSWIRTSCHAFTSLEHRE - BACHELOR OF SCIENCE 15 --- Page 20 --- Gültig für Studierende der PO 2021 (Einschreibung ab WiSe 2021/22) MODULHANDBUCH - VOLKSWIRTSCHAFTSLEHRE - BACHELOR OF SCIENCE 16 --- Page 21 --- Gültig für Studierende der PO 2021 (Einschreibung ab WiSe 2021/22) MODULHANDBUCH - VOLKSWIRTSCHAFTSLEHRE - BACHELOR OF SCIENCE 17 Hinweis zum Wahlbereich VWL soz.: Falls d', '- Gültig für Studierende der PO 2021 (Einschreibung ab WiSe 2021/22) MODULHANDBUCH - VOLKSWIRTSCHAFTSLEHRE - BACHELOR OF SCIENCE 109 Ergänzungsbereich Sozialwissenschaften - Soziologie Bachelor of Arts Regionalstudien Lateinamerika - Sozialwissenschaften: Ergänzungsbereich Sozialwissenschaften - Politikwissenschaft Bachelor of Arts Regionalstudien Ost - und Mitteleuropa - Sozialwissenschaften: Ergänzungsbereich Sozialwissenschaften - Politikwissenschaft Bachelor of Arts Regionalst udien China - Betriebswirtschaftslehre: Ergänzungsbereich BWL Bachelor of Arts Regionalstudien China - Volkswirtschaftslehre: Ergänzungsbereich VWL Bachelor of Science Management, Economics and Social Sciences: Schwerpunktbereich Management, Economics and Social Sciences Bachelor of Arts Regionalstudien China - Sozialwissenschaften: Ergänzungsbereich SoWi Bachelor of Science Volkswirtschaftslehre: Schwerpunktbereich Studienrichtung VWL Schwerpunkt Studienrichtung BWL Schwerpunkt Studienrichtung Sozialwissenschaften Bachelor of Science Sozialwissenschaften: Ergänzungsbereich Sozialwissenschaften 9 Modulbeauftragte/r Univ. -Prof. Dr.‘ Martina Fuchs 10 Sonstige Informationen --- Page 114 --- Gültig für Studierende der PO 2021 (Einschreibung ab WiSe 2021/22) MODULHANDBUCH - VOLKSWIRTSCHAFTSLEHRE - BACHELOR OF SCIENCE 110 EM Kooperatives Wirtschaften Kennnummer 1344BEKOW1 Workload 180h LP 6 Modulsprache Deutsch Modulbeginn jedes 2. Semester - Wintersemester Moduldauer 1 Semester 1 Lehrveranstaltungen Soz'] | H11: ['file://D:/Uni-Köln/Masterarbeit/Software/uzk-masterarbeit/data/pdf_cache/__wiso.uni-koeln.de_sites_fakultaet_dokumente_downloads_Modulhandbuecher_Studienjahr_22-23_MHB_PO2021_b_mhb_po2021_vwl.pdf', 'file://D:/Uni-Köln/Masterarbeit/Software/uzk-masterarbeit/data/pdf_cache/__wiso.uni-koeln.de_sites_fakultaet_dokumente_downloads_bachelor_b_mhb_po2021_vwl.pdf', 'file://D:/Uni-Köln/Masterarbeit/Software/uzk-masterarbeit/data/pdf_cache/__wiso.uni-koeln.de_sites_fakultaet_dokumente_downloads_Modulhandbuecher_Studienjahr_22-23_MHB_PO2021_b_mhb_po2021_vwl.pdf', 'file://D:/Uni-Köln/Masterarbeit/Software/uzk-masterarbeit/data/pdf_cache/__wiso.uni-koeln.de_sites_fakultaet_dokumente_downloads_bachelor_b_mhb_po2021_vwl.pdf', 'file://D:/Uni-Köln/Masterarbeit/Software/uzk-masterarbeit/data/pdf_cache/__wiso.uni-koeln.de_sites_fakultaet_dokumente_downloads_Modulhandbuecher_Bachelor_MHB_aktuelles_Studienjahr_b_mhb_po2021_vwl.pdf'] | I11: ['pdf', 'pdf', 'pdf', 'pdf', 'pdf'] | J11: 1 | K11: 1 | L11: 1 | M11: 0.82410898 | N11: 0 | O11: 0.94654205 | P11: 0.69018906 | Q11: 0.73658782 | R11: 0.64316595 | S11: 0 | T11: 0 | U11: 7.532701 | V11: 2441 | W11: 66 | X11: 2507 | Y11: 0 | Z11: 5 | AA11: 7.532701
A12: 11 | B12: Modulhandbuch/PO | C12: medium | D12: Welche Bachelorstudiengänge der WiSo-Fakultät haben ein eigenes Modulhandbuch unter PO 2021? | E12: Basierend auf den Suchergebnissen können wir folgende Bachelorstudiengänge der WiSo-Fakultät identifizieren, die ein eigenes Modulhandbuch unter PO 2021 haben: * Betriebswirtschaftslehre (BWL) * Sozialwissenschaften Bitte beachten Sie, dass diese Informationen auf den Suchergebnissen basieren und möglicherweise nicht vollständig oder aktuell sind. Es ist immer ratsam, direkt bei der Universität zu überprüfen, ob die Informationen noch gültig sind. | F12: Für das Studienjahr 2025/26 gibt es unter der Bachelor PO 2021 Modulhandbücher für Betriebswirtschaftslehre, Volkswirtschaftslehre, Management, Economics and Social Sciences, Sozialwissenschaften, Gesundheitsökonomie, Wirtschaftsinformatik sowie Lehramt am Berufskolleg I. | G12: ['# Modulhandbuch-Archiv\n\nHier Sie die Modulhandbücher (MHB) aller WiSo-Studiengänge vergangener Studienjahre ab dem Studienjahr 2021/22. Bitte beachten Sie, dass diese MHB keine Gültigkeit mehr besitzen.\xa0\n\n## Inhaltsverzeichnis\n\n- Bachelor\n\n- Bachelor PO 2021\n- Bachelor PO 2015\n\xa0\n\n- Master\n\n- Master PO 2021\n- Master PO 2015\n\nAchten Sie zudem auch auf die entsprechende Prüfungsordnung (PO). Die PO 2021 gilt ab dem Studienjahr 2021/22; die PO 2015 ist für Masterstudiengänge im Studienjahr 2022/23 ausgelaufen und für Bachelorstudiengänge zum Studienjahr 2024/25.\n\n\xa0\n\nFalls Sie ein MHB aus einem anderen Studienjahr benötigen, dann können Sie sich gerne über das Kontaktformular an den WiSo Student Service Point wenden.\n\n## Bachelor PO 2021\n\n## Bachelor Modulhandbücher | gültig vom 01.10.2024-30.09.2025\n\nNachfolgend Sie für jeden Bachelorstudiengang\xa0das Modulhandbuch der Prüfungsordnung PO 2021 gültig für das Studienjahr 2024/25.\n\n- Betriebswirtschaftslehre\n- Volkswirtschaftslehre\n- Management, Economics and Social Sciences\n- Sozialwissenschaften\n- Gesundheitsökonomie\n- Wirtschaftsinformatik\n- Lehramt am Berufskolleg I\n\n## Bachelor Modulhandbücher | gültig vom 01.10.2023-30.09.2024\n\nNachfolgend Sie für jeden Bachelorstudiengang\xa0das Modulhandbuch der Prüfungsordnung PO 2021 gültig für das Studienjahr 2023/24.\n\n- Betriebswirtschaftslehre\n- Volkswirtschaftslehre\n- Management, Economics and Social Sciences\n- Sozialwissenschaften\n- Gesundheitsökonomie\n- Wirtschaftsinformatik\n- Lehramt am', 'Dokumente und Medien - Prüfungsordnung 2021\n\n# Bachelor PO 2021\n\nHier Sie alle wichtigen Dokumente, die Sie zur Orientierung und für die Organisation Ihres Studiums benötigen.\xa0\n\nGültig für Studierende der Prüfungsordnung 2021 (Einschreibung ab WiSe 2021/22).\n\nIm Modulhandbuch-Archiv Sie die Modulhandbücher vergangener Studienjahre.\n\n## Bachelor Modulhandbücher | gültig vom 01.10.2025-30.09.2026\n\nNachfolgend Sie für jeden Bachelorstudiengang\xa0das Modulhandbuch der Prüfungsordnung PO 2021 gültig ab dem 01.10.2025.\n\n- Betriebswirtschaftslehre\n- Volkswirtschaftslehre\n- Management, Economics and Social Sciences\n- Sozialwissenschaften\n- Gesundheitsökonomie\n- Wirtschaftsinformatik\n- Lehramt am Berufskolleg I\n\n## Prüfungsordnungen PO 2021\n\nIm Download-Bereich des Prüfungsamtes Sie die gemeinsame Prüfungsordnung der WiSo-Studiengänge, sowie die zusätzliche Bachelorprüfungsordnung.\n\nHI\n\nzum Seitenanfang', '--- Page 1 --- Bitte beachten Sie das G ültigkeitsjahr des Modulhandbuchs 2024/25 WIRTSCHAFTS - UND SOZIALWISSENSCHAFTLICHE FAKULTÄT UNIVERSITÄT ZU KÖLN STUDIENDEKANAT MODULHANDBUCH BETRIEBSWIRTSCHAFTSLEHRE BACHELOR OF SCIENCE NACH DER PRÜFUNGSORDNUNG FÜR DEN 1 -FACH -BACHELOR -STUDIENGANG BETRIEBSWIRTSCHAFTSLEHRE Gültig für Studierende der Prüfungsordnung 2021 (Einschreibung ab WiSe 2021/22) --- Page 2 --- Gültig für Studierende der PO 2021 (Einschreibung ab WiSe 2021/22) MODULHANDBUCH – BETRIEBSWIRTSCHAFTSLEHRE – BACHELOR OF SCIENCE 2 Akademische Direktor in Univ. -Prof. Dr. ‘ Franziska Völckner Programm -Direktor AD. Dr. Johannes Antweiler Herausgeber/ Redaktion Studiendekanat der Wirtschafts - und Sozialwissenschaftli- chen Fakultät Studienberatung WiSo -Student Service Point (WiSSPo) +49 (0) 221 / 470 - 8818 www.wiso.uni- koeln.de/anfrage Stand Gültig ab 01.10.202 4 --- Page 3 --- Gültig für Studierende der PO 2021 (Einschreibung ab WiSe 2021/22) MODULHANDBUCH – BETRIEBSWIRTSCHAFTSLEHRE – BACHELOR OF SCIENCE 3 Legende AM Aufbaumodul P Pflichtveranstaltung AN Anrechnung PB Praktikumsbericht AS Assignment PO Portfolio BM Basismodul PR Projekt EM Ergänzungsmodul RE Referat FS Fallstudie SM Schwerpunktmodul HA Hausarbeit SSt Selbststudium K Kontaktzeit (= Präsenzzeit in LV) SWS Semesterwochenstunde KL Klausur SI Studium Integrale LP Leistungspunkt (engl.: CP) VN Vor- und Nachbereitungszeit LV Lehrveranstaltung WP Wahlpflichtveranstaltung MP Mündliche Prüfung WL Workload = Ar', '--- Page 1 --- Bitte beachten Sie das G ültigkeitsjahr des Modulhandbuchs 2025/26 WIRTSCHAFTS - UND SOZIALWISSENSCHAFTLICHE FAKULTÄT UNIVERSITÄT ZU KÖLN STUDIENDEKANAT MODULHANDBUCH BETRIEBSWIRTSCHAFTSLEHRE BACHELOR OF SCIENCE NACH DER PRÜFUNGSORDNUNG FÜR DEN 1 -FACH -BACHELOR -STUDIENGANG BETRIEBSWIRTSCHAFTSLEHRE Gültig für Studierende der Prüfungsordnung 2021 (Einschreibung ab WiSe 2021/22) --- Page 2 --- Gültig für Studierende der PO 2021 (Einschreibung ab WiSe 2021/22) MODULHANDBUCH – BETRIEBSWIRTSCHAFTSLEHRE – BACHELOR OF SCIENCE 2 Akademische Direktor in Univ. -Prof. Dr. ‘ Franziska Völckner Programm -Direktor AD. Dr. Johannes Antweiler Herausgeber/ Redaktion Studiendekanat der Wirtschafts - und Sozialwissenschaftlichen Fakultät Studienberatung WiSo -Student Se rvice Point (WiSSPo) +49 (0) 221 / 470 - 8818 www.wiso.uni -koeln.de/anfrage Stand Gültig ab 01.10.20 25 --- Page 3 --- Gültig für Studierende der PO 2021 (Einschreibung ab WiSe 2021/22) MODULHANDBUCH – BETRIEBSWIRTSCHAFTSLEHRE – BACHELOR OF SCIENCE 3 Legende AM Aufbaumodul P Pflichtveranstaltung AN Anrechnung PB Praktikumsbericht AS Assignment PO Portfolio BM Basismodul PR Projekt EM Ergänzungsmodul RE Referat FS Fallstudie SM Schwerpunktmodul HA Hausarbeit SSt Selbststudium K Kontaktzeit (= Präsenzzeit in LV) SWS Semesterwochenstunde KL Klausur SI Studium Integrale LP Leistungspunkt (engl.: CP) VN Vor- und Nachbereitungszeit LV Lehrveranstaltung WP Wahlpflichtveranstaltung MP Mündliche Prüfung WL Workload = Arb', '--- Page 1 --- Bitte beachten Sie das Gültigkeitsjahr des Modulhandbuchs . 2024/25 WIRTSCHAFTS - UND SOZIALWISSENSCHAFTLICHE FAKULTÄT UNIVERSITÄT ZU KÖLN STUDIENDEKANAT MODULHANDBUCH SOZIALWISSENSCHAFTEN BACHELOR OF SCIENCE NACH DER PRÜFUNGSORDNUNG FÜR DEN 1 -FACH -BACHELOR -STUDIENGANG SOZIALWISSENSCHAFTEN Gültig für Studierende der Prüfungsordnung 2021 (Einschreibung ab WiSe 2021/22) --- Page 2 --- Gültig für Studierende der PO 2021 (Einschreibung ab WiSe 2021/22) MODULHANDBUCH - SOZIALWISSENSCHAFTEN - BACHELOR OF SCIENCE ii Akademischer Direktor Prof. Dr. Detlef Fetchenhauer Programm -Direktoren Dr. Birgit Bujard Dr. Andr é Ernst Herausgeber/ Redaktion Studiendekanat der Wirtschafts - und Sozialwissenschaftlichen Fakultät Studienberatung WiSo -Student Service Point (WiSSPo) +49 (0) 221 / 470 - 8818 www.wiso.uni -koeln.de/anfrage Stand Gültig ab 01.10.2024 --- Page 3 --- Gültig für Studierende der PO 2021 (Einschreibung ab WiSe 2021/22) MODULHANDBUCH - SOZIALWISSENSCHAFTEN - BACHELOR OF SCIENCE iii Legende AM Aufbaumodul P Pflichtveranstaltung AN Anrechnung PB Praktikumsbericht AS Assignment PO Portfolio BM Basismodul PR Projekt EM Ergänzungsmodul RE Referat FS Fallstudie SM Schwerpunktmodul HA Hausarbeit SSt Selbststudium K Kontaktzeit (= Präsenzzeit in LV) SWS Semesterwochenstunde KL Klausur SI Studium Integrale LP Leistungspunkt (engl.: CP) VN Vor- und Nachbereitungszeit LV Lehrveranstaltung WP Wahlpflichtveranstaltung MP Mündliche Prüfung WL Workload = Arbeitsaufwand --'] | H12: ['https://wiso.uni-koeln.de/de/studium/modulhandbuecher-und-pruefungsordnungen/modulhandbuch-archiv', 'https://wiso.uni-koeln.de/de/studium/modulhandbuecher-und-pruefungsordnungen/bachelor-po-2021', 'file://D:/Uni-Köln/Masterarbeit/Software/uzk-masterarbeit/data/pdf_cache/__wiso.uni-koeln.de_sites_fakultaet_dokumente_downloads_bachelor_b_mhb_po2021_bwl.pdf', 'file://D:/Uni-Köln/Masterarbeit/Software/uzk-masterarbeit/data/pdf_cache/__wiso.uni-koeln.de_sites_fakultaet_dokumente_downloads_Modulhandbuecher_Bachelor_MHB_aktuelles_Studienjahr_b_mhb_po2021_bwl.pdf', 'file://D:/Uni-Köln/Masterarbeit/Software/uzk-masterarbeit/data/pdf_cache/__wiso.uni-koeln.de_sites_fakultaet_dokumente_downloads_bachelor_b_mhb_po2021_sowi.pdf'] | I12: ['html', 'html', 'pdf', 'pdf', 'pdf'] | J12: 0.6 | K12: 1 | L12: 1 | M12: 0.70005895 | N12: 0.7 | O12: 0 | P12: 0.16519766 | Q12: 0.035858162 | R12: 0.29711905 | S12: 0.5 | T12: 1 | U12: 15.589101 | V12: 2533 | W12: 160 | X12: 2693 | Y12: 0 | Z12: 5 | AA12: 15.589101
A13: 12 | B13: Modulhandbuch/PO | C13: easy | D13: Wo finden Bachelorstudierende die zugehörigen Prüfungsordnungen der PO 2021? | E13: Die Prüfungsordnungen (PO) für den Bachelor-Studiengang PO 2021 können auf der Website der Universität zu Köln unter "Modulhandbücher" > "Bachelor" > "PO 2021" gefunden werden. Dort sind die jeweiligen Modulhandbücher und Prüfungsordnungen für das Studienjahr 2021/22 und später abrufbar. Alternativ können Sie auch auf der Website der WiSo-Fakultät unter "Studium" > "Modulhandbücher" nachsehen, ob dort die PO 2021 verfügbar sind. Es ist jedoch ratsam, direkt auf der Universitäts-Website zu suchen, da dort die aktuellsten Informationen zur Verfügung stehen. Wenn Sie Schwierigkeiten haben, die Prüfungsordnungen zu finden oder Fragen dazu haben, können Sie sich gerne an die Studienberatung wenden. | F13: Im Download-Bereich des Prüfungsamtes finden Sie die gemeinsame Prüfungsordnung der WiSo-Studiengänge, sowie die zusätzliche Bachelorprüfungsordnung. | G13: ['der PO 2021 (Einschreibung ab WiSe 2021/22) MODULHANDBUCH - VOLKSWIRTSCHAFTSLEHRE - BACHELOR OF SCIENCE 13 --- Page 18 --- Gültig für Studierende der PO 2021 (Einschreibung ab WiSe 2021/22) MODULHANDBUCH - VOLKSWIRTSCHAFTSLEHRE - BACHELOR OF SCIENCE 14 --- Page 19 --- Gültig für Studierende der PO 2021 (Einschreibung ab WiSe 2021/22) MODULHANDBUCH - VOLKSWIRTSCHAFTSLEHRE - BACHELOR OF SCIENCE 15 --- Page 20 --- Gültig für Studierende der PO 2021 (Einschreibung ab WiSe 2021/22) MODULHANDBUCH - VOLKSWIRTSCHAFTSLEHRE - BACHELOR OF SCIENCE 16 Hinweis zum Wahlbereich VWL soz.: Falls der Master in Social and Economic Psychology angestrebt wird, sollte das Modul BM Einführung in die Psychologie ( 1320BBWPS1) spätestens im vorletzten Semester belegt werden. --- Page 21 --- Gültig für Studierende der PO 2021 (Einschreibung ab WiSe 2021/22) MODULHANDBUCH - VOLKSWIRTSCHAFTSLEHRE - BACHELOR OF SCIENCE 17 --- Page 22 --- Gültig für Studierende der PO 2021 (Einschreibung ab WiSe 2021/22) MODULHANDBUCH - VOLKSWIRTSCHAFTSLEHRE - BACHELOR OF SCIENCE 18 Hinweis zum Wahlbereich VWL soz.: Falls der Master in Social and Economic Psychology angestrebt wird, sollte das Modul BM Einführung in die Psychologie (1320BBWPS1) spätestens im vorletzten Semester belegt werden. --- Page 23 --- Gültig für Studierende der PO 2021 (Einschreibung ab WiSe 2021/22) MODULHANDBUCH - VOLKSWIRTSCHAFTSLEHRE - BACHELOR OF SCIENCE 19 --- Page 24 --- Gültig für Studierende der PO 2021 (Einschreibung ab WiSe 2021/22) MODUL', 'rende der PO 2021 (Einschreibung ab WiSe 2021/22) MODULHANDBUCH - VOLKSWIRTSCHAFTSLEHRE - BACHELOR OF SCIENCE 16 --- Page 21 --- Gültig für Studierende der PO 2021 (Einschreibung ab WiSe 2021/22) MODULHANDBUCH - VOLKSWIRTSCHAFTSLEHRE - BACHELOR OF SCIENCE 17 Hinweis zum Wahlbereich VWL soz.: Falls der Master in Social and Economic Psychology angestrebt wird, sollte das Modul BM Einführung in die Psychologie (1320BBWPS1) spätestens im vorletzten Semester belegt werden. --- Page 22 --- Gültig für Studierende der PO 2021 (Einschreibung ab WiSe 2021/22) MODULHANDBUCH - VOLKSWIRTSCHAFTSLEHRE - BACHELOR OF SCIENCE 18 --- Page 23 --- Gültig für Studierende der PO 2021 (Einschreibung ab WiSe 2021/22) MODULHANDBUCH - VOLKSWIRTSCHAFTSLEHRE - BACHELOR OF SCIENCE 19 Hinweis zum Wahlbereich VWL soz.: Falls der Master in Social and Economic Psychology angestrebt wird, sollte das Modul BM Einführung in die Psychologie (1320BBWPS1) spätestens im vorletzten Semester belegt werden. --- Page 24 --- Gültig für Studierende der PO 2021 (Einschreibung ab WiSe 2021/22) MODULHANDBUCH - VOLKSWIRTSCHAFTSLEHRE - BACHELOR OF SCIENCE 20 --- Page 25 --- Gültig für Studierende der PO 2021 (Einschreibung ab WiSe 2021/22) MODULHANDBUCH - VOLKSWIRTSCHAFTSLEHRE - BACHELOR OF SCIENCE 21 Hinweis zum Wahlbereich VWL soz. (1/2) : Falls der Master in Politikwissenschaft angestrebt wird, soll te das Modul SM Vertiefung Politikwissenschaft (1335BSVPW1) spätestens im vorletzten Semester belegt werden. Hinweis zum Wahlb', '# Modulhandbuch-Archiv\n\nHier Sie die Modulhandbücher (MHB) aller WiSo-Studiengänge vergangener Studienjahre ab dem Studienjahr 2021/22. Bitte beachten Sie, dass diese MHB keine Gültigkeit mehr besitzen.\xa0\n\n## Inhaltsverzeichnis\n\n- Bachelor\n\n- Bachelor PO 2021\n- Bachelor PO 2015\n\xa0\n\n- Master\n\n- Master PO 2021\n- Master PO 2015\n\nAchten Sie zudem auch auf die entsprechende Prüfungsordnung (PO). Die PO 2021 gilt ab dem Studienjahr 2021/22; die PO 2015 ist für Masterstudiengänge im Studienjahr 2022/23 ausgelaufen und für Bachelorstudiengänge zum Studienjahr 2024/25.\n\n\xa0\n\nFalls Sie ein MHB aus einem anderen Studienjahr benötigen, dann können Sie sich gerne über das Kontaktformular an den WiSo Student Service Point wenden.\n\n## Bachelor PO 2021\n\n## Bachelor Modulhandbücher | gültig vom 01.10.2024-30.09.2025\n\nNachfolgend Sie für jeden Bachelorstudiengang\xa0das Modulhandbuch der Prüfungsordnung PO 2021 gültig für das Studienjahr 2024/25.\n\n- Betriebswirtschaftslehre\n- Volkswirtschaftslehre\n- Management, Economics and Social Sciences\n- Sozialwissenschaften\n- Gesundheitsökonomie\n- Wirtschaftsinformatik\n- Lehramt am Berufskolleg I\n\n## Bachelor Modulhandbücher | gültig vom 01.10.2023-30.09.2024\n\nNachfolgend Sie für jeden Bachelorstudiengang\xa0das Modulhandbuch der Prüfungsordnung PO 2021 gültig für das Studienjahr 2023/24.\n\n- Betriebswirtschaftslehre\n- Volkswirtschaftslehre\n- Management, Economics and Social Sciences\n- Sozialwissenschaften\n- Gesundheitsökonomie\n- Wirtschaftsinformatik\n- Lehramt am', 'Semester ). --- Page 12 --- Gültig für Studierende der PO 2021 (Einschreibung ab WiSe 2021/22) MODULHANDBUCH - VOLKSWIRTSCHAFTSLEHRE - BACHELOR OF SCIENCE 8 Hinweis zum Wahlbereich VWL: Falls der Master in Social and Economic Psychology angestrebt wird, sollte das Modul BM Einführu ng in die Psychologie (1320BBWPS1) spätestens im vorletzten Semester belegt werden. --- Page 13 --- Gültig für Studierende der PO 2021 (Einschreibung ab WiSe 2021/22) MODULHANDBUCH - VOLKSWIRTSCHAFTSLEHRE - BACHELOR OF SCIENCE 9 --- Page 14 --- Gültig für Studierende der PO 2021 (Einschreibung ab WiSe 2021/22) MODULHANDBUCH - VOLKSWIRTSCHAFTSLEHRE - BACHELOR OF SCIENCE 10 Hinweis zum Wahlbereich VWL: Falls der Master in Social and Economic Psychology angestrebt wird, sollte das Modul BM Einführu ng in die Psychologie (1320BBWPS1) spätestens im vorletzten Semester belegt werden. --- Page 15 --- Gültig für Studierende der PO 2021 (Einschreibung ab WiSe 2021/22) MODULHANDBUCH - VOLKSWIRTSCHAFTSLEHRE - BACHELOR OF SCIENCE 11 --- Page 16 --- Gültig für Studierende der PO 2021 (Einschreibung ab WiSe 2021/22) MODULHANDBUCH - VOLKSWIRTSCHAFTSLEHRE - BACHELOR OF SCIENCE 12 --- Page 17 --- Gültig für Studierende der PO 2021 (Einschreibung ab WiSe 2021/22) MODULHANDBUCH - VOLKSWIRTSCHAFTSLEHRE - BACHELOR OF SCIENCE 13 --- Page 18 --- Gültig für Studierende der PO 2021 (Einschreibung ab WiSe 2021/22) MODULHANDBUCH - VOLKSWIRTSCHAFTSLEHRE - BACHELOR OF SCIENCE 14 --- Page 19 --- Gültig für Studierende der PO 2', 'in die Psychologie (1320BBWPS1) spätestens im vorletzten Semester belegt werden. --- Page 14 --- Gültig für Studierende der PO 2021 (Einschreibung ab WiSe 2021/22) MODULHANDBUCH - VOLKSWIRTSCHAFTSLEHRE - BACHELOR OF SCIENCE 10 --- Page 15 --- Gültig für Studierende der PO 2021 (Einschreibung ab WiSe 2021/22) MODULHANDBUCH - VOLKSWIRTSCHAFTSLEHRE - BACHELOR OF SCIENCE 11 Hinweis zum Wahlbereich VWL: Falls der Master in Social and Economic Psychology angestrebt wird, sollte das Modul BM Einführu ng in die Psychologie (1320BBWPS1) spätestens im vorletzten Semester belegt werden. --- Page 16 --- Gültig für Studierende der PO 2021 (Einschreibung ab WiSe 2021/22) MODULHANDBUCH - VOLKSWIRTSCHAFTSLEHRE - BACHELOR OF SCIENCE 12 --- Page 17 --- Gültig für Studierende der PO 2021 (Einschreibung ab WiSe 2021/22) MODULHANDBUCH - VOLKSWIRTSCHAFTSLEHRE - BACHELOR OF SCIENCE 13 --- Page 18 --- Gültig für Studierende der PO 2021 (Einschreibung ab WiSe 2021/22) MODULHANDBUCH - VOLKSWIRTSCHAFTSLEHRE - BACHELOR OF SCIENCE 14 --- Page 19 --- Gültig für Studierende der PO 2021 (Einschreibung ab WiSe 2021/22) MODULHANDBUCH - VOLKSWIRTSCHAFTSLEHRE - BACHELOR OF SCIENCE 15 --- Page 20 --- Gültig für Studierende der PO 2021 (Einschreibung ab WiSe 2021/22) MODULHANDBUCH - VOLKSWIRTSCHAFTSLEHRE - BACHELOR OF SCIENCE 16 --- Page 21 --- Gültig für Studierende der PO 2021 (Einschreibung ab WiSe 2021/22) MODULHANDBUCH - VOLKSWIRTSCHAFTSLEHRE - BACHELOR OF SCIENCE 17 Hinweis zum Wahlbereich VWL soz.: Falls d'] | H13: ['file://D:/Uni-Köln/Masterarbeit/Software/uzk-masterarbeit/data/pdf_cache/__wiso.uni-koeln.de_sites_fakultaet_dokumente_downloads_Modulhandbuecher_Studienjahr_22-23_MHB_PO2021_b_mhb_po2021_vwl.pdf', 'file://D:/Uni-Köln/Masterarbeit/Software/uzk-masterarbeit/data/pdf_cache/__wiso.uni-koeln.de_sites_fakultaet_dokumente_downloads_bachelor_b_mhb_po2021_vwl.pdf', 'https://wiso.uni-koeln.de/de/studium/modulhandbuecher-und-pruefungsordnungen/modulhandbuch-archiv', 'file://D:/Uni-Köln/Masterarbeit/Software/uzk-masterarbeit/data/pdf_cache/__wiso.uni-koeln.de_sites_fakultaet_dokumente_downloads_Modulhandbuecher_Studienjahr_22-23_MHB_PO2021_b_mhb_po2021_vwl.pdf', 'file://D:/Uni-Köln/Masterarbeit/Software/uzk-masterarbeit/data/pdf_cache/__wiso.uni-koeln.de_sites_fakultaet_dokumente_downloads_bachelor_b_mhb_po2021_vwl.pdf'] | I13: ['pdf', 'pdf', 'html', 'pdf', 'pdf'] | J13: 0.5 | K13: 0 | L13: 0 | M13: 0.64255838 | N13: 0.2 | O13: 0.81648447 | P13: 0.18791126 | Q13: -0.022571236 | R13: 0.41216004 | S13: 0 | T13: 0 | U13: 12.155341 | V13: 2463 | W13: 234 | X13: 2697 | Y13: 0 | Z13: 5 | AA13: 12.155341
... A117: 116 | B117: PDF-Spezifisch | C117: medium | D117: Welche ersten Schritte soll ich laut Notfallplan unternehmen, wenn ich einen Viren- oder Trojanerbefall vermute? | E117: Es tut mir leid, aber ich konnte keine spezifischen Schritte für den Notfallplan Viren- oder Trojanerbefall finden. Es ist jedoch ratsam, folgende allgemeine Schritte zu unternehmen: 1. **Sofortiges Handeln**: Wenn Sie einen Viren- oder Trojanerbefall vermuten, sollten Sie sofort handeln und nicht warten, bis der Schaden größer wird. 2. **System-Neustart**: Ein System-Neustart kann oft helfen, den Befall zu beheben. 3. **Virenskanner verwenden**: Installieren und starten Sie einen Virenskanner, um den Computer auf Viren oder Trojaner zu scannen und zu entfernen. 4. **System-Wiederherstellung**: Wenn der Befall schwerwiegend ist, sollten Sie die System-Wiederherstellung nutzen, um das System in einen vor dem Befall gesicherten Zustand zurückzusetzen. 5. **Professionelle Hilfe**: Wenn Sie nicht sicher sind, wie Sie vorgehen sollen oder wenn der Befall schwerwiegend ist, sollten Sie sich an einen IT-Experten wenden. Bitte beachten Sie, dass diese Schritte allgemeiner Natur sind und je nach Art des Viren- oder Trojanerbefalls spezifische Maßnahmen erforderlich sein können. | F117: Wenn du einen Viren- oder Trojanerbefall vermutest, sollst du laut Notfallplan zunächst Ruhe bewahren. Danach trennst du deinen Rechner vom Netzwerk, indem du das Netzwerkkabel ziehst oder die WLAN-Verbindung beendest, damit sich die Schadsoftware nicht weiterverbreiten kann. Anschließend kontaktierst du die WiSo-IT unter der Telefonnummer -6630 oder per E-Mail an support@wiso.uni-koeln.de und hältst Informationen zu deinem Betriebssystem, deinem Account, weiteren Nutzer:innen des Rechners und dem verwendeten Virenscanner bereit. | G117: ['--- Page 1 --- Tel. (0221) 470 – 6630 support@wiso.uni -koeln.de Universität zu Köln Wirtschafts - und Sozialwissenschaftliche Fakultät WiSo IT -Services Stand: 28.07.2020 Notfallplan Viren und Trojanerbefall Ihr Computer verhält sich anders als sonst? Sie befürchten einen Viren - oder Trojanerbefall? Anzeichen eines Viren befalls: Es werden unvermutet Programme gestartet. Ihre Suchanfragen werden ständig umgeleitet . Ihr Rechner ist ständig überlastet . Sie entdecken zunehmend sehr lange und sehr kryptische Dateinamen. Sie sehen ungewöhnliche Warnhinweise auf dem Desktop . Bitte halten Sie f olgende Informationen bereit : Welches Betriebssystem nutzen Sie? Mit welchem Account sind Sie auf dem Rechner eingeloggt? Gibt es noch andere Personen , welche diesen Rechner nutzen? Welchen Virenscanner nutzen Sie? Schritt 1 Bewahren Sie Ruhe! Schritt 2 Ziehen Sie das Netzwerkkabel bzw. beenden Sie die WLAN -Verbindung. Es ist wichtig, dass sich die Schadsoftware nicht weiterverbreiten kann. Schritt 3 Kontaktieren Sie die WiSo -IT unter -6630 oder support@wi so.uni -koeln.de', '; versehentlich gelöschte Daten können von uns in vielen Fällen wiederhergestellt werden. Die lokale Festplatte ist nur für Ihr Betriebssystem und Ihre installierte Software gedacht, die man jederzeit ersetzen und neu aufspielen kann.\n\n## Vermeiden Sie potentiell gefährliche Dateianhänge\n\nZusätzlich zur Überprüfung von Mails blockiert auf dem Exchange-Server der Virenscanner PureMessage Dateianhänge anhand der Dateiendung und anhand des Dateityps.\nDie Blockierung erfolgt sowohl bei ein- als auch ausgehendenden Mails. Eine Liste der geblockten Dateiendungen Sie auf dem Public-Laufwerk.\n\n## Verwenden Sie einen aktuellen Virenschutz\n\nAn der Universität zu Köln sollten Sie den für alle Mitarbeiter*innen kostenlos verwendbaren Cisco Secure Endpoint benutzen. Aus Lizenzgründen sind Sie nicht berechtigt, auf Dienstrechnern "freie" Antivirus-Programme zu nutzen (z.B. AntiVir).\n\n- Sophos Antivirus am RRZK\n\n## Beachten Sie unsere Notfall-Hinweise\n\nSofern Ihr Rechner trotz aller Vorsicht von einem Virus befallen ist oder Sie einen Befall vermuten, hilft Ihnen unser Notfallplan mit ersten wichtigen Schritten weiter.\n\n- Notfallplan\n\nHI\n\nTo top of page', '; versehentlich gelöschte Daten können von uns in vielen Fällen wiederhergestellt werden. Die lokale Festplatte ist nur für Ihr Betriebssystem und Ihre installierte Software gedacht, die man jederzeit ersetzen und neu aufspielen kann.\n\n## Vermeiden Sie potentiell gefährliche Dateianhänge\n\nZusätzlich zur Überprüfung von Mails blockiert auf dem Exchange-Server der Virenscanner PureMessage Dateianhänge anhand der Dateiendung und anhand des Dateityps.\nDie Blockierung erfolgt sowohl bei ein- als auch ausgehendenden Mails. Eine Liste der geblockten Dateiendungen Sie auf dem Public-Laufwerk.\n\n## Verwenden Sie einen aktuellen Virenschutz\n\nAn der Universität zu Köln sollten Sie den für alle Mitarbeiter*innen kostenlos verwendbaren Cisco Secure Endpoint benutzen. Aus Lizenzgründen sind Sie nicht berechtigt, auf Dienstrechnern "freie" Antivirus-Programme zu nutzen (z.B. AntiVir).\n\n- Sophos Antivirus am RRZK\n\n## Beachten Sie unsere Notfall-Hinweise\n\nSofern Ihr Rechner trotz aller Vorsicht von einem Virus befallen ist oder Sie einen Befall vermuten, hilft Ihnen unser Notfallplan mit ersten wichtigen Schritten weiter.\n\n- Notfallplan\n\nHI\n\nzum Seitenanfang', 'von der Lehrperson alle Fenster zu schließen und die Lichter auszuschalten. (5) Sachgerechte Nutzung der bereitgestellten Hard - und Software Damit die volle Funkti onsfähigkeit der PC-Pools den Benutzer/innen erhalten bleibt, ist es nicht gestattet, Veränderungen an der vorgefundenen Hard - und Software vorzunehmen. Dazu gehört auch, dass die vorhandenen Geräte nicht geöffnet oder auf andere Weise verändert werden. Die Nutzung eigener externer Datenträger (z.B. USB -Sticks) bleib t von dieser Regelung unberührt . An den Programmen dürfen keine Änderungen und Löschungen vorgenommen werden. Das gilt sowohl für Anwendungssoftware, als auch für das Betriebssystem und dessen Konfiguration. Die Installation mitgebrachter oder aus dem Internet geladene r Programme ist nicht zulässig. (6) Fehlermeldungen Defekte, Fehler und Funktionsabweichunge n melden Sie bitte umgehend der WiSo -IT. (7) Virenschutz Die Computer sind mit Virenschutzprogrammen ausgerüstet. Dennoch trägt jeder/jede Benutzer/in selbst die Verantwortung dafür, dass erstens durch sie/ihn keine Viren auf die Computer gelangen und dass zweitens eigene Dateien und Datenträger nicht mit Viren infiziert werden. Wenn Sie dennoch auf einem hochschuleigenen Rechner einen Virus feststellen sollten, beenden Sie bitte die Arbeit an dem Gerät, sperren es mit einem Warnhinweis und verständigen umgehend die WiSo -IT. --- Page 2 --- Tel. (0221) 470 – 6630 2 Universität zu Köln Wirtschafts - und Sozialwissenschaftliche Fakultät WiSo', 'Webseite des Prüfungsamts bekanntge- gebenen elektronischen Übermittlungsweg angezeigt und nachgewiesen werden. 3Dasselbe gilt, wenn eine Prüfungsleistung nicht innerhalb der vorgegebenen Bearbeitungszeit erbracht wird. 4Bei Krankheit ist die Vorl age einer ärztlichen Bescheinigung notwendig. 5In Zweifelsfällen kann die Vor- lage eines vertrauensärztlichen Attests verlangt werden; die Kosten übernimmt die Universität. 6Glei- ches gilt bei nachgewiesener Erkrankung eines von einer Prüfungskandidatin bezi ehungsweise ei- nem Prüfungskandidaten zu versorgenden Kindes oder einer zu pflegenden Ehegattin oder eines zu pflegenden Ehegatten, einer eingetragenen Lebenspartnerin oder eines eingetragenen Lebenspart- ners, einer oder eines in gerader Linie Verwandten sow ie einer oder eines im ersten Grad Verschwä- gerten. 7Alles weitere regelt der jeweils zuständigen Prüfungsausschuss. --- Page 27 --- 27 § 17 Nachteilsausgleich und Schutzbestimmungen (1) Die besonderen Belange von Studierenden mit Behinderungen, chronischen oder psychi- schen Erkrankungen und Studierenden, die den mutterschutzrechtlichen Bestimmungen unterliegen, sind zur Wahrnehmung ihrer Chancengleichheit zu berücksichtigen. (2) 1Macht eine Prüfungskandidatin oder ein Prüfungskandidat glaubhaft, dass sie oder er w e- gen länger andauernder oder ständiger Krankheit oder Behinderung nicht in der Lage ist, an einer Prüfung in der vorgesehenen Form oder in dem vorgesehenen Umfang teilzunehmen, wird ihr oder ihm auf schri'] | H117: ['file://D:/Uni-Köln/Masterarbeit/Software/uzk-masterarbeit/data/pdf_cache/__wiso.uni-koeln.de_sites_wiso_it_docs_sicherheit_Sicherheit-Notfallplan-Viren-und-Trojaner.pdf', 'https://wiso.uni-koeln.de/en/services/it/sicherheit', 'https://wiso.uni-koeln.de/de/services/it/sicherheit', 'file://D:/Uni-Köln/Masterarbeit/Software/uzk-masterarbeit/data/pdf_cache/__wiso.uni-koeln.de_sites_wiso_it_docs_Anleitungen_PC-Pool_Benutzungsordnung.pdf', 'file://D:/Uni-Köln/Masterarbeit/Software/uzk-masterarbeit/data/pdf_cache/__wiso.uni-koeln.de_sites_fakultaet_dokumente_PA_po_GPO_2025.pdf'] | I117: ['pdf', 'html', 'html', 'pdf', 'pdf'] | J117: 0.42857143 | K117: 1 | L117: 1 | M117: 0.72210492 | N117: 0.46153846 | O117: 0 | P117: 0.053422913 | Q117: 0.039976858 | R117: 0.062709965 | S117: 1 | T117: 1 | U117: 57.756553 | V117: 2260 | W117: 331 | X117: 2591 | Y117: 0 | Z117: 5 | AA117: 57.756553

Sheet Zusammenfassung
A1: 📊 RAGAS-Evaluation Zusammenfassung
A3: Durchschnittliche Scores
A4: faithfulness | B4: =AVERAGE('Detaillierte Ergebnisse'!J2:J117) -> 0.63211653
A5: context_recall | B5: =AVERAGE('Detaillierte Ergebnisse'!K2:K117) -> 0.66497845
A6: context_precision | B6: =AVERAGE('Detaillierte Ergebnisse'!L2:L117) -> 0.63939176
A7: semantic_similarity | B7: =AVERAGE('Detaillierte Ergebnisse'!M2:M117) -> 0.75045523
A8: context_entity_recall | B8: =AVERAGE('Detaillierte Ergebnisse'!N2:N117) -> 0.29335766
A9: answer_relevancy | B9: =AVERAGE('Detaillierte Ergebnisse'!O2:O117) -> 0.56451632
A10: BERT-F1 | B10: =AVERAGE('Detaillierte Ergebnisse'!P2:P117) -> 0.24253653
A11: BERT-Precision | B11: =AVERAGE('Detaillierte Ergebnisse'!Q2:Q117) -> 0.19350583
A12: BERT-Recall | B12: =AVERAGE('Detaillierte Ergebnisse'!R2:R117) -> 0.29250682
A13: MRR@5 | B13: =AVERAGE('Detaillierte Ergebnisse'!S2:S117) -> 0.37514368
A14: Hit@5 | B14: =AVERAGE('Detaillierte Ergebnisse'!T2:T117) -> 0.51724138
A15: latency | B15: =AVERAGE('Detaillierte Ergebnisse'!U2:U117) -> 17.643618
A16: Prompt Tokens (avg) | B16: =AVERAGE('Detaillierte Ergebnisse'!V2:V117) -> 2232
A17: Completion Tokens (avg) | B17: =AVERAGE('Detaillierte Ergebnisse'!W2:W117) -> 217.83621
A18: Total Tokens (avg) | B18: =AVERAGE('Detaillierte Ergebnisse'!X2:X117) -> 2449.8362
A19: ReRanking Tokens (avg) | B19: =AVERAGE('Detaillierte Ergebnisse'!Y2:Y117) -> 0
A22: Scores nach Kategorie
A23: Kategorie | B23: Faithfulness | C23: Context Recall | D23: Context Precision | E23: Semantic Similarity | F23: Context Entity Recall | G23: Answer Relevancy | H23: BERT-F1 | I23: BERT-Precision | J23: BERT-Recall | K23: MRR@5 | L23: Hit@5 | M23: Latency | N23: (Input) Tokens | O23: (Output) Tokens | P23: Gesamt Tokens | Q23: ReRanking Tokens
A24: Allgemein | B24: =AVERAGEIFS('Detaillierte Ergebnisse'!J2:J117,'Detaillierte Ergebnisse'!$B$2:$B$117, $A$24) -> 0.6086326 | C24: =AVERAGEIFS('Detaillierte Ergebnisse'!$K$2:$K$117,'Detaillierte Ergebnisse'!$B$2:$B$117, $A24) -> 0.64583333 | D24: =AVERAGEIFS('Detaillierte Ergebnisse'!$L$2:$L$117,'Detaillierte Ergebnisse'!$B$2:$B$117, $A24) -> 0.48055556 | E24: =AVERAGEIFS('Detaillierte Ergebnisse'!$M$2:$M$117,'Detaillierte Ergebnisse'!$B$2:$B$117, $A24) -> 0.69754109 | F24: =AVERAGEIFS('Detaillierte Ergebnisse'!$N2:$N117,'Detaillierte Ergebnisse'!$B$2:$B$117, $A24) -> 0.21595569 | G24: =AVERAGEIFS('Detaillierte Ergebnisse'!$O$2:$O$117,'Detaillierte Ergebnisse'!$B$2:$B$117, $A24) -> 0.73625965 | H24: =AVERAGEIFS('Detaillierte Ergebnisse'!$P$2:$P$117,'Detaillierte Ergebnisse'!$B$2:$B$117, $A24) -> 0.1865825 | I24: =AVERAGEIFS('Detaillierte Ergebnisse'!$Q$2:$Q$117,'Detaillierte Ergebnisse'!$B$2:$B$117, $A24) -> 0.11867641 | J24: =AVERAGEIFS('Detaillierte Ergebnisse'!$R$2:$R$117,'Detaillierte Ergebnisse'!$B$2:$B$117, $A24) -> 0.2544127 | K24: =AVERAGEIFS('Detaillierte Ergebnisse'!$S$2:$S$117,'Detaillierte Ergebnisse'!$B$2:$B$117, $A24) -> 0.29444444 | L24: =AVERAGEIFS('Detaillierte Ergebnisse'!$T$2:$T$117,'Detaillierte Ergebnisse'!$B$2:$B$117, $A24) -> 0.41666667 | M24: =AVERAGEIFS('Detaillierte Ergebnisse'!$U$2:$U$117,'Detaillierte Ergebnisse'!$B$2:$B$117, $A24) -> 14.26495 | N24: =AVERAGEIFS('Detaillierte Ergebnisse'!$V$2:$V$117,'Detaillierte Ergebnisse'!$B$2:$B$117, $A24) -> 2239.1667 | O24: =AVERAGEIFS('Detaillierte Ergebnisse'!$W$2:$W$117,'Detaillierte Ergebnisse'!$B$2:$B$117, $A24) -> 250.25 | P24: =AVERAGEIFS('Detaillierte Ergebnisse'!$X$2:$X$117,'Detaillierte Ergebnisse'!$B$2:$B$117, $A24) -> 2489.4167 | Q24: =AVERAGEIFS('Detaillierte Ergebnisse'!$Y$2:$Y$117,'Detaillierte Ergebnisse'!$B$2:$B$117, $A24) -> 0
A25: Bachelor-Studium | B25: =AVERAGEIFS('Detaillierte Ergebnisse'!$J$2:$J$117,'Detaillierte Ergebnisse'!$B$2:$B$117, A25) -> 0.62205387 | C25: =AVERAGEIFS('Detaillierte Ergebnisse'!$K$2:$K$117,'Detaillierte Ergebnisse'!$B$2:$B$117, $A25) -> 0.61111111 | D25: =AVERAGEIFS('Detaillierte Ergebnisse'!$L$2:$L$117,'Detaillierte Ergebnisse'!$B$2:$B$117, $A25) -> 0.83395062 | E25: =AVERAGEIFS('Detaillierte Ergebnisse'!$M$2:$M$117,'Detaillierte Ergebnisse'!$B$2:$B$117, $A25) -> 0.79912317 | F25: =AVERAGEIFS('Detaillierte Ergebnisse'!$N3:$N118,'Detaillierte Ergebnisse'!$B$2:$B$117, $A25) -> 0.44373898 | G25: =AVERAGEIFS('Detaillierte Ergebnisse'!$O$2:$O$117,'Detaillierte Ergebnisse'!$B$2:$B$117, $A25) -> 0.48043169 | H25: =AVERAGEIFS('Detaillierte Ergebnisse'!$P$2:$P$117,'Detaillierte Ergebnisse'!$B$2:$B$117, $A25) -> 0.29462825 | I25: =AVERAGEIFS('Detaillierte Ergebnisse'!$Q$2:$Q$117,'Detaillierte Ergebnisse'!$B$2:$B$117, $A25) -> 0.16181531 | J25: =AVERAGEIFS('Detaillierte Ergebnisse'!$R$2:$R$117,'Detaillierte Ergebnisse'!$B$2:$B$117, $A25) -> 0.43275304 | K25: =AVERAGEIFS('Detaillierte Ergebnisse'!$S$2:$S$117,'Detaillierte Ergebnisse'!$B$2:$B$117, $A25) -> 0.53703704 | L25: =AVERAGEIFS('Detaillierte Ergebnisse'!$T$2:$T$117,'Detaillierte Ergebnisse'!$B$2:$B$117, $A25) -> 0.77777778 | M25: =AVERAGEIFS('Detaillierte Ergebnisse'!$U$2:$U$117,'Detaillierte Ergebnisse'!$B$2:$B$117, $A25) -> 12.337716 | N25: =AVERAGEIFS('Detaillierte Ergebnisse'!$V$2:$V$117,'Detaillierte Ergebnisse'!$B$2:$B$117, $A25) -> 2255.8889 | O25: =AVERAGEIFS('Detaillierte Ergebnisse'!$W$2:$W$117,'Detaillierte Ergebnisse'!$B$2:$B$117, $A25) -> 220.33333 | P25: =AVERAGEIFS('Detaillierte Ergebnisse'!$X$2:$X$117,'Detaillierte Ergebnisse'!$B$2:$B$117, $A25) -> 2476.2222 | Q25: =AVERAGEIFS('Detaillierte Ergebnisse'!$Y$2:$Y$117,'Detaillierte Ergebnisse'!$B$2:$B$117, $A25) -> 0
A26: FAQ | B26: =AVERAGEIFS('Detaillierte Ergebnisse'!$J$2:$J$117,'Detaillierte Ergebnisse'!$B$2:$B$117, A26) -> 0.60869748 | C26: =AVERAGEIFS('Detaillierte Ergebnisse'!$K$2:$K$117,'Detaillierte Ergebnisse'!$B$2:$B$117, $A26) -> 0.7725 | D26: =AVERAGEIFS('Detaillierte Ergebnisse'!$L$2:$L$117,'Detaillierte Ergebnisse'!$B$2:$B$117, $A26) -> 0.66861111 | E26: =AVERAGEIFS('Detaillierte Ergebnisse'!$M$2:$M$117,'Detaillierte Ergebnisse'!$B$2:$B$117, $A26) -> 0.74507863 | F26: =AVERAGEIFS('Detaillierte Ergebnisse'!$N4:$N119,'Detaillierte Ergebnisse'!$B$2:$B$117, $A26) -> 0.42772988 | G26: =AVERAGEIFS('Detaillierte Ergebnisse'!$O$2:$O$117,'Detaillierte Ergebnisse'!$B$2:$B$117, $A26) -> 0.35253427 | H26: =AVERAGEIFS('Detaillierte Ergebnisse'!$P$2:$P$117,'Detaillierte Ergebnisse'!$B$2:$B$117, $A26) -> 0.20519892 | I26: =AVERAGEIFS('Detaillierte Ergebnisse'!$Q$2:$Q$117,'Detaillierte Ergebnisse'!$B$2:$B$117, $A26) -> 0.24296539 | J26: =AVERAGEIFS('Detaillierte Ergebnisse'!$R$2:$R$117,'Detaillierte Ergebnisse'!$B$2:$B$117, $A26) -> 0.16603837 | K26: =AVERAGEIFS('Detaillierte Ergebnisse'!$S$2:$S$117,'Detaillierte Ergebnisse'!$B$2:$B$117, $A26) -> 0.53333333 | L26: =AVERAGEIFS('Detaillierte Ergebnisse'!$T$2:$T$117,'Detaillierte Ergebnisse'!$B$2:$B$117, $A26) -> 0.73333333 | M26: =AVERAGEIFS('Detaillierte Ergebnisse'!$U$2:$U$117,'Detaillierte Ergebnisse'!$B$2:$B$117, $A26) -> 11.971523 | N26: =AVERAGEIFS('Detaillierte Ergebnisse'!$V$2:$V$117,'Detaillierte Ergebnisse'!$B$2:$B$117, $A26) -> 2242.8 | O26: =AVERAGEIFS('Detaillierte Ergebnisse'!$W$2:$W$117,'Detaillierte Ergebnisse'!$B$2:$B$117, $A26) -> 191.6 | P26: =AVERAGEIFS('Detaillierte Ergebnisse'!$X$2:$X$117,'Detaillierte Ergebnisse'!$B$2:$B$117, $A26) -> 2434.4 | Q26: =AVERAGEIFS('Detaillierte Ergebnisse'!$Y$2:$Y$117,'Detaillierte Ergebnisse'!$B$2:$B$117, $A26) -> 0
A27: International | B27: =AVERAGEIFS('Detaillierte Ergebnisse'!$J$2:$J$117,'Detaillierte Ergebnisse'!$B$2:$B$117, A27) -> 0.71333333 | C27: =AVERAGEIFS('Detaillierte Ergebnisse'!$K$2:$K$117,'Detaillierte Ergebnisse'!$B$2:$B$117, $A27) -> 0.8 | D27: =AVERAGEIFS('Detaillierte Ergebnisse'!$L$2:$L$117,'Detaillierte Ergebnisse'!$B$2:$B$117, $A27) -> 0.655 | E27: =AVERAGEIFS('Detaillierte Ergebnisse'!$M$2:$M$117,'Detaillierte Ergebnisse'!$B$2:$B$117, $A27) -> 0.83526564 | F27: =AVERAGEIFS('Detaillierte Ergebnisse'!$N5:$N120,'Detaillierte Ergebnisse'!$B$2:$B$117, $A27) -> 0.34212185 | G27: =AVERAGEIFS('Detaillierte Ergebnisse'!$O$2:$O$117,'Detaillierte Ergebnisse'!$B$2:$B$117, $A27) -> 0.56401434 | H27: =AVERAGEIFS('Detaillierte Ergebnisse'!$P$2:$P$117,'Detaillierte Ergebnisse'!$B$2:$B$117, $A27) -> 0.27526262 | I27: =AVERAGEIFS('Detaillierte Ergebnisse'!$Q$2:$Q$117,'Detaillierte Ergebnisse'!$B$2:$B$117, $A27) -> 0.22943276 | J27: =AVERAGEIFS('Detaillierte Ergebnisse'!$R$2:$R$117,'Detaillierte Ergebnisse'!$B$2:$B$117, $A27) -> 0.31920036 | K27: =AVERAGEIFS('Detaillierte Ergebnisse'!$S$2:$S$117,'Detaillierte Ergebnisse'!$B$2:$B$117, $A27) -> 0.11666667 | L27: =AVERAGEIFS('Detaillierte Ergebnisse'!$T$2:$T$117,'Detaillierte Ergebnisse'!$B$2:$B$117, $A27) -> 0.4 | M27: =AVERAGEIFS('Detaillierte Ergebnisse'!$U$2:$U$117,'Detaillierte Ergebnisse'!$B$2:$B$117, $A27) -> 12.60837 | N27: =AVERAGEIFS('Detaillierte Ergebnisse'!$V$2:$V$117,'Detaillierte Ergebnisse'!$B$2:$B$117, $A27) -> 2123.4 | O27: =AVERAGEIFS('Detaillierte Ergebnisse'!$W$2:$W$117,'Detaillierte Ergebnisse'!$B$2:$B$117, $A27) -> 245.8 | P27: =AVERAGEIFS('Detaillierte Ergebnisse'!$X$2:$X$117,'Detaillierte Ergebnisse'!$B$2:$B$117, $A27) -> 2369.2 | Q27: =AVERAGEIFS('Detaillierte Ergebnisse'!$Y$2:$Y$117,'Detaillierte Ergebnisse'!$B$2:$B$117, $A27) -> 0
A28: Master-Studium | B28: =AVERAGEIFS('Detaillierte Ergebnisse'!$J$2:$J$117,'Detaillierte Ergebnisse'!$B$2:$B$117, A28) -> 0.76296296 | C28: =AVERAGEIFS('Detaillierte Ergebnisse'!$K$2:$K$117,'Detaillierte Ergebnisse'!$B$2:$B$117, $A28) -> 0.66666667 | D28: =AVERAGEIFS('Detaillierte Ergebnisse'!$L$2:$L$117,'Detaillierte Ergebnisse'!$B$2:$B$117, $A28) -> 0.61111111 | E28: =AVERAGEIFS('Detaillierte Ergebnisse'!$M$2:$M$117,'Detaillierte Ergebnisse'!$B$2:$B$117, $A28) -> 0.80106205 | F28: =AVERAGEIFS('Detaillierte Ergebnisse'!$N6:$N121,'Detaillierte Ergebnisse'!$B$2:$B$117, $A28) -> 0.70833333 | G28: =AVERAGEIFS('Detaillierte Ergebnisse'!$O$2:$O$117,'Detaillierte Ergebnisse'!$B$2:$B$117, $A28) -> 0.60791032 | H28: =AVERAGEIFS('Detaillierte Ergebnisse'!$P$2:$P$117,'Detaillierte Ergebnisse'!$B$2:$B$117, $A28) -> 0.38469556 | I28: =AVERAGEIFS('Detaillierte Ergebnisse'!$Q$2:$Q$117,'Detaillierte Ergebnisse'!$B$2:$B$117, $A28) -> 0.20829821 | J28: =AVERAGEIFS('Detaillierte Ergebnisse'!$R$2:$R$117,'Detaillierte Ergebnisse'!$B$2:$B$117, $A28) -> 0.57061947 | K28: =AVERAGEIFS('Detaillierte Ergebnisse'!$S$2:$S$117,'Detaillierte Ergebnisse'!$B$2:$B$117, $A28) -> 0.16666667 | L28: =AVERAGEIFS('Detaillierte Ergebnisse'!$T$2:$T$117,'Detaillierte Ergebnisse'!$B$2:$B$117, $A28) -> 0.33333333 | M28: =AVERAGEIFS('Detaillierte Ergebnisse'!$U$2:$U$117,'Detaillierte Ergebnisse'!$B$2:$B$117, $A28) -> 13.052874 | N28: =AVERAGEIFS('Detaillierte Ergebnisse'!$V$2:$V$117,'Detaillierte Ergebnisse'!$B$2:$B$117, $A28) -> 2262.3333 | O28: =AVERAGEIFS('Detaillierte Ergebnisse'!$W$2:$W$117,'Detaillierte Ergebnisse'!$B$2:$B$117, $A28) -> 234.66667 | P28: =AVERAGEIFS('Detaillierte Ergebnisse'!$X$2:$X$117,'Detaillierte Ergebnisse'!$B$2:$B$117, $A28) -> 2497 | Q28: =AVERAGEIFS('Detaillierte Ergebnisse'!$Y$2:$Y$117,'Detaillierte Ergebnisse'!$B$2:$B$117, $A28) -> 0
A29: Modulhandbuch/PO | B29: =AVERAGEIFS('Detaillierte Ergebnisse'!$J$2:$J$117,'Detaillierte Ergebnisse'!$B$2:$B$117, A29) -> 0.53809524 | C29: =AVERAGEIFS('Detaillierte Ergebnisse'!$K$2:$K$117,'Detaillierte Ergebnisse'!$B$2:$B$117, $A29) -> 0.57142857 | D29: =AVERAGEIFS('Detaillierte Ergebnisse'!$L$2:$L$117,'Detaillierte Ergebnisse'!$B$2:$B$117, $A29) -> 0.57142857 | E29: =AVERAGEIFS('Detaillierte Ergebnisse'!$M$2:$M$117,'Detaillierte Ergebnisse'!$B$2:$B$117, $A29) -> 0.72308437 | F29: =AVERAGEIFS('Detaillierte Ergebnisse'!$N7:$N122,'Detaillierte Ergebnisse'!$B$2:$B$117, $A29) -> 0.30680272 | G29: =AVERAGEIFS('Detaillierte Ergebnisse'!$O$2:$O$117,'Detaillierte Ergebnisse'!$B$2:$B$117, $A29) -> 0.7378772 | H29: =AVERAGEIFS('Detaillierte Ergebnisse'!$P$2:$P$117,'Detaillierte Ergebnisse'!$B$2:$B$117, $A29) -> 0.3395519 | I29: =AVERAGEIFS('Detaillierte Ergebnisse'!$Q$2:$Q$117,'Detaillierte Ergebnisse'!$B$2:$B$117, $A29) -> 0.30572483 | J29: =AVERAGEIFS('Detaillierte Ergebnisse'!$R$2:$R$117,'Detaillierte Ergebnisse'!$B$2:$B$117, $A29) -> 0.37629839 | K29: =AVERAGEIFS('Detaillierte Ergebnisse'!$S$2:$S$117,'Detaillierte Ergebnisse'!$B$2:$B$117, $A29) -> 0.071428571 | L29: =AVERAGEIFS('Detaillierte Ergebnisse'!$T$2:$T$117,'Detaillierte Ergebnisse'!$B$2:$B$117, $A29) -> 0.14285714 | M29: =AVERAGEIFS('Detaillierte Ergebnisse'!$U$2:$U$117,'Detaillierte Ergebnisse'!$B$2:$B$117, $A29) -> 10.479121 | N29: =AVERAGEIFS('Detaillierte Ergebnisse'!$V$2:$V$117,'Detaillierte Ergebnisse'!$B$2:$B$117, $A29) -> 2308.1429 | O29: =AVERAGEIFS('Detaillierte Ergebnisse'!$W$2:$W$117,'Detaillierte Ergebnisse'!$B$2:$B$117, $A29) -> 127.71429 | P29: =AVERAGEIFS('Detaillierte Ergebnisse'!$X$2:$X$117,'Detaillierte Ergebnisse'!$B$2:$B$117, $A29) -> 2435.8571 | Q29: =AVERAGEIFS('Detaillierte Ergebnisse'!$Y$2:$Y$117,'Detaillierte Ergebnisse'!$B$2:$B$117, $A29) -> 0
A30: PDF-Spezifisch | B30: =AVERAGEIFS('Detaillierte Ergebnisse'!$J$2:$J$117,'Detaillierte Ergebnisse'!$B$2:$B$117, A30) -> 0.55734671 | C30: =AVERAGEIFS('Detaillierte Ergebnisse'!$K$2:$K$117,'Detaillierte Ergebnisse'!$B$2:$B$117, $A30) -> 0.6828125 | D30: =AVERAGEIFS('Detaillierte Ergebnisse'!$L$2:$L$117,'Detaillierte Ergebnisse'!$B$2:$B$117, $A30) -> 0.68224826 | E30: =AVERAGEIFS('Detaillierte Ergebnisse'!$M$2:$M$117,'Detaillierte Ergebnisse'!$B$2:$B$117, $A30) -> 0.76100783 | F30: =AVERAGEIFS('Detaillierte Ergebnisse'!$N8:$N123,'Detaillierte Ergebnisse'!$B$2:$B$117, $A30) -> 0.19313037 | G30: =AVERAGEIFS('Detaillierte Ergebnisse'!$O$2:$O$117,'Detaillierte Ergebnisse'!$B$2:$B$117, $A30) -> 0.55399104 | H30: =AVERAGEIFS('Detaillierte Ergebnisse'!$P$2:$P$117,'Detaillierte Ergebnisse'!$B$2:$B$117, $A30) -> 0.23516971 | I30: =AVERAGEIFS('Detaillierte Ergebnisse'!$Q$2:$Q$117,'Detaillierte Ergebnisse'!$B$2:$B$117, $A30) -> 0.16690124 | J30: =AVERAGEIFS('Detaillierte Ergebnisse'!$R$2:$R$117,'Detaillierte Ergebnisse'!$B$2:$B$117, $A30) -> 0.30460523 | K30: =AVERAGEIFS('Detaillierte Ergebnisse'!$S$2:$S$117,'Detaillierte Ergebnisse'!$B$2:$B$117, $A30) -> 0.42291667 | L30: =AVERAGEIFS('Detaillierte Ergebnisse'!$T$2:$T$117,'Detaillierte Ergebnisse'!$B$2:$B$117, $A30) -> 0.5 | M30: =AVERAGEIFS('Detaillierte Ergebnisse'!$U$2:$U$117,'Detaillierte Ergebnisse'!$B$2:$B$117, $A30) -> 30.818417 | N30: =AVERAGEIFS('Detaillierte Ergebnisse'!$V$2:$V$117,'Detaillierte Ergebnisse'!$B$2:$B$117, $A30) -> 2264.0625 | O30: =AVERAGEIFS('Detaillierte Ergebnisse'!$W$2:$W$117,'Detaillierte Ergebnisse'!$B$2:$B$117, $A30) -> 240.375 | P30: =AVERAGEIFS('Detaillierte Ergebnisse'!$X$2:$X$117,'Detaillierte Ergebnisse'!$B$2:$B$117, $A30) -> 2504.4375 | Q30: =AVERAGEIFS('Detaillierte Ergebnisse'!$Y$2:$Y$117,'Detaillierte Ergebnisse'!$B$2:$B$117, $A30) -> 0
A31: Services/Info | B31: =AVERAGEIFS('Detaillierte Ergebnisse'!$J$2:$J$117,'Detaillierte Ergebnisse'!$B$2:$B$117, A31) -> 0.75689391 | C31: =AVERAGEIFS('Detaillierte Ergebnisse'!$K$2:$K$117,'Detaillierte Ergebnisse'!$B$2:$B$117, $A31) -> 0.74561404 | D31: =AVERAGEIFS('Detaillierte Ergebnisse'!$L$2:$L$117,'Detaillierte Ergebnisse'!$B$2:$B$117, $A31) -> 0.74239766 | E31: =AVERAGEIFS('Detaillierte Ergebnisse'!$M$2:$M$117,'Detaillierte Ergebnisse'!$B$2:$B$117, $A31) -> 0.735559 | F31: =AVERAGEIFS('Detaillierte Ergebnisse'!$N9:$N124,'Detaillierte Ergebnisse'!$B$2:$B$117, $A31) -> 0.21690784 | G31: =AVERAGEIFS('Detaillierte Ergebnisse'!$O$2:$O$117,'Detaillierte Ergebnisse'!$B$2:$B$117, $A31) -> 0.5277307 | H31: =AVERAGEIFS('Detaillierte Ergebnisse'!$P$2:$P$117,'Detaillierte Ergebnisse'!$B$2:$B$117, $A31) -> 0.2552056 | I31: =AVERAGEIFS('Detaillierte Ergebnisse'!$Q$2:$Q$117,'Detaillierte Ergebnisse'!$B$2:$B$117, $A31) -> 0.25358957 | J31: =AVERAGEIFS('Detaillierte Ergebnisse'!$R$2:$R$117,'Detaillierte Ergebnisse'!$B$2:$B$117, $A31) -> 0.25760388 | K31: =AVERAGEIFS('Detaillierte Ergebnisse'!$S$2:$S$117,'Detaillierte Ergebnisse'!$B$2:$B$117, $A31) -> 0.48421053 | L31: =AVERAGEIFS('Detaillierte Ergebnisse'!$T$2:$T$117,'Detaillierte Ergebnisse'!$B$2:$B$117, $A31) -> 0.68421053 | M31: =AVERAGEIFS('Detaillierte Ergebnisse'!$U$2:$U$117,'Detaillierte Ergebnisse'!$B$2:$B$117, $A31) -> 11.852341 | N31: =AVERAGEIFS('Detaillierte Ergebnisse'!$V$2:$V$117,'Detaillierte Ergebnisse'!$B$2:$B$117, $A31) -> 2201 | O31: =AVERAGEIFS('Detaillierte Ergebnisse'!$W$2:$W$117,'Detaillierte Ergebnisse'!$B$2:$B$117, $A31) -> 189 | P31: =AVERAGEIFS('Detaillierte Ergebnisse'!$X$2:$X$117,'Detaillierte Ergebnisse'!$B$2:$B$117, $A31) -> 2390 | Q31: =AVERAGEIFS('Detaillierte Ergebnisse'!$Y$2:$Y$117,'Detaillierte Ergebnisse'!$B$2:$B$117, $A31) -> 0
A32: Studiengang spezifisch | B32: =AVERAGEIFS('Detaillierte Ergebnisse'!$J$2:$J$117,'Detaillierte Ergebnisse'!$B$2:$B$117, A32) -> 0.67533417 | C32: =AVERAGEIFS('Detaillierte Ergebnisse'!$K$2:$K$117,'Detaillierte Ergebnisse'!$B$2:$B$117, $A32) -> 0.44880952 | D32: =AVERAGEIFS('Detaillierte Ergebnisse'!$L$2:$L$117,'Detaillierte Ergebnisse'!$B$2:$B$117, $A32) -> 0.41587302 | E32: =AVERAGEIFS('Detaillierte Ergebnisse'!$M$2:$M$117,'Detaillierte Ergebnisse'!$B$2:$B$117, $A32) -> 0.73893211 | F32: =AVERAGEIFS('Detaillierte Ergebnisse'!$N10:$N125,'Detaillierte Ergebnisse'!$B$2:$B$117, $A32) -> 0.2659333 | G32: =AVERAGEIFS('Detaillierte Ergebnisse'!$O$2:$O$117,'Detaillierte Ergebnisse'!$B$2:$B$117, $A32) -> 0.67666702 | H32: =AVERAGEIFS('Detaillierte Ergebnisse'!$P$2:$P$117,'Detaillierte Ergebnisse'!$B$2:$B$117, $A32) -> 0.20600064 | I32: =AVERAGEIFS('Detaillierte Ergebnisse'!$Q$2:$Q$117,'Detaillierte Ergebnisse'!$B$2:$B$117, $A32) -> 0.13218338 | J32: =AVERAGEIFS('Detaillierte Ergebnisse'!$R$2:$R$117,'Detaillierte Ergebnisse'!$B$2:$B$117, $A32) -> 0.27919251 | K32: =AVERAGEIFS('Detaillierte Ergebnisse'!$S$2:$S$117,'Detaillierte Ergebnisse'!$B$2:$B$117, $A32) -> 0.20238095 | L32: =AVERAGEIFS('Detaillierte Ergebnisse'!$T$2:$T$117,'Detaillierte Ergebnisse'!$B$2:$B$117, $A32) -> 0.28571429 | M32: =AVERAGEIFS('Detaillierte Ergebnisse'!$U$2:$U$117,'Detaillierte Ergebnisse'!$B$2:$B$117, $A32) -> 14.137846 | N32: =AVERAGEIFS('Detaillierte Ergebnisse'!$V$2:$V$117,'Detaillierte Ergebnisse'!$B$2:$B$117, $A32) -> 2161.9286 | O32: =AVERAGEIFS('Detaillierte Ergebnisse'!$W$2:$W$117,'Detaillierte Ergebnisse'!$B$2:$B$117, $A32) -> 235.64286 | P32: =AVERAGEIFS('Detaillierte Ergebnisse'!$X$2:$X$117,'Detaillierte Ergebnisse'!$B$2:$B$117, $A32) -> 2397.5714 | Q32: =AVERAGEIFS('Detaillierte Ergebnisse'!$Y$2:$Y$117,'Detaillierte Ergebnisse'!$B$2:$B$117, $A32) -> 0
A35: Scores nach Schwierigkeit
A36: Schwierigkeit | B36: Faithfulness | C36: Context Recall | D36: Context Precision | E36: Semantic Similarity | F36: Context Entity Recall | G36: Answer Relevancy | H36: BERT-F1 | I36: BERT-Precision | J36: BERT-Recall | K36: MRR@5 | L36: Hit@5 | M36: Latency | N36: (Input) Tokens | O36: (Output) Tokens | P36: Gesamt Tokens | Q36: ReRanking Tokens
A37: EASY | B37: =AVERAGEIFS('Detaillierte Ergebnisse'!$J$2:$J$117,'Detaillierte Ergebnisse'!$C$2:$C$117, A37) -> 0.63182547 | C37: =AVERAGEIFS('Detaillierte Ergebnisse'!$K$2:$K$117,'Detaillierte Ergebnisse'!$C$2:$C$117, $A37) -> 0.70454545 | D37: =AVERAGEIFS('Detaillierte Ergebnisse'!$L$2:$L$117,'Detaillierte Ergebnisse'!$C$2:$C$117, $A37) -> 0.60248316 | E37: =AVERAGEIFS('Detaillierte Ergebnisse'!$M$2:$M$117,'Detaillierte Ergebnisse'!$C$2:$C$117, $A37) -> 0.7350518 | F37: =AVERAGEIFS('Detaillierte Ergebnisse'!$N15:$N130,'Detaillierte Ergebnisse'!$C$2:$C$117, $A37) -> 0.37363361 | G37: =AVERAGEIFS('Detaillierte Ergebnisse'!$O$2:$O$117,'Detaillierte Ergebnisse'!$C$2:$C$117, $A37) -> 0.58642721 | H37: =AVERAGEIFS('Detaillierte Ergebnisse'!$P$2:$P$117,'Detaillierte Ergebnisse'!$C$2:$C$117, $A37) -> 0.32378444 | I37: =AVERAGEIFS('Detaillierte Ergebnisse'!$Q$2:$Q$117,'Detaillierte Ergebnisse'!$C$2:$C$117, $A37) -> 0.21186667 | J37: =AVERAGEIFS('Detaillierte Ergebnisse'!$R$2:$R$117,'Detaillierte Ergebnisse'!$C$2:$C$117, $A37) -> 0.44060325 | K37: =AVERAGEIFS('Detaillierte Ergebnisse'!$S$2:$S$117,'Detaillierte Ergebnisse'!$C$2:$C$117, $A37) -> 0.25454545 | L37: =AVERAGEIFS('Detaillierte Ergebnisse'!$T$2:$T$117,'Detaillierte Ergebnisse'!$C$2:$C$117, $A37) -> 0.42424242 | M37: =AVERAGEIFS('Detaillierte Ergebnisse'!$U$2:$U$117,'Detaillierte Ergebnisse'!$C$2:$C$117, $A37) -> 13.124968 | N37: =AVERAGEIFS('Detaillierte Ergebnisse'!$V$2:$V$117,'Detaillierte Ergebnisse'!$C$2:$C$117, $A37) -> 2225.3333 | O37: =AVERAGEIFS('Detaillierte Ergebnisse'!$W$2:$W$117,'Detaillierte Ergebnisse'!$C$2:$C$117, $A37) -> 179.42424 | P37: =AVERAGEIFS('Detaillierte Ergebnisse'!$X$2:$X$117,'Detaillierte Ergebnisse'!$C$2:$C$117, $A37) -> 2404.7576 | Q37: =AVERAGEIFS('Detaillierte Ergebnisse'!$Y$2:$Y$117,'Detaillierte Ergebnisse'!$C$2:$C$117, $A37) -> 0
A38: MEDIUM | B38: =AVERAGEIFS('Detaillierte Ergebnisse'!$J$2:$J$117,'Detaillierte Ergebnisse'!$C$2:$C$117, A38) -> 0.66190029 | C38: =AVERAGEIFS('Detaillierte Ergebnisse'!$K$2:$K$117,'Detaillierte Ergebnisse'!$C$2:$C$117, $A38) -> 0.69972678 | D38: =AVERAGEIFS('Detaillierte Ergebnisse'!$L$2:$L$117,'Detaillierte Ergebnisse'!$C$2:$C$117, $A38) -> 0.66773679 | E38: =AVERAGEIFS('Detaillierte Ergebnisse'!$M$2:$M$117,'Detaillierte Ergebnisse'!$C$2:$C$117, $A38) -> 0.75907799 | F38: =AVERAGEIFS('Detaillierte Ergebnisse'!$N16:$N131,'Detaillierte Ergebnisse'!$C$2:$C$117, $A38) -> 0.28099215 | G38: =AVERAGEIFS('Detaillierte Ergebnisse'!$O$2:$O$117,'Detaillierte Ergebnisse'!$C$2:$C$117, $A38) -> 0.55050842 | H38: =AVERAGEIFS('Detaillierte Ergebnisse'!$P$2:$P$117,'Detaillierte Ergebnisse'!$C$2:$C$117, $A38) -> 0.23051212 | I38: =AVERAGEIFS('Detaillierte Ergebnisse'!$Q$2:$Q$117,'Detaillierte Ergebnisse'!$C$2:$C$117, $A38) -> 0.19576817 | J38: =AVERAGEIFS('Detaillierte Ergebnisse'!$R$2:$R$117,'Detaillierte Ergebnisse'!$C$2:$C$117, $A38) -> 0.26501812 | K38: =AVERAGEIFS('Detaillierte Ergebnisse'!$S$2:$S$117,'Detaillierte Ergebnisse'!$C$2:$C$117, $A38) -> 0.46092896 | L38: =AVERAGEIFS('Detaillierte Ergebnisse'!$T$2:$T$117,'Detaillierte Ergebnisse'!$C$2:$C$117, $A38) -> 0.62295082 | M38: =AVERAGEIFS('Detaillierte Ergebnisse'!$U$2:$U$117,'Detaillierte Ergebnisse'!$C$2:$C$117, $A38) -> 19.07363 | N38: =AVERAGEIFS('Detaillierte Ergebnisse'!$V$2:$V$117,'Detaillierte Ergebnisse'!$C$2:$C$117, $A38) -> 2243.0328 | O38: =AVERAGEIFS('Detaillierte Ergebnisse'!$W$2:$W$117,'Detaillierte Ergebnisse'!$C$2:$C$117, $A38) -> 232.47541 | P38: =AVERAGEIFS('Detaillierte Ergebnisse'!$X$2:$X$117,'Detaillierte Ergebnisse'!$C$2:$C$117, $A38) -> 2475.5082 | Q38: =AVERAGEIFS('Detaillierte Ergebnisse'!$Y$2:$Y$117,'Detaillierte Ergebnisse'!$C$2:$C$117, $A38) -> 0
A39: HARD | B39: =AVERAGEIFS('Detaillierte Ergebnisse'!$J$2:$J$117,'Detaillierte Ergebnisse'!$C$2:$C$117, A39) -> 0.54997088 | C39: =AVERAGEIFS('Detaillierte Ergebnisse'!$K$2:$K$117,'Detaillierte Ergebnisse'!$C$2:$C$117, $A39) -> 0.5092803 | D39: =AVERAGEIFS('Detaillierte Ergebnisse'!$L$2:$L$117,'Detaillierte Ergebnisse'!$C$2:$C$117, $A39) -> 0.61616162 | E39: =AVERAGEIFS('Detaillierte Ergebnisse'!$M$2:$M$117,'Detaillierte Ergebnisse'!$C$2:$C$117, $A39) -> 0.74965182 | F39: =AVERAGEIFS('Detaillierte Ergebnisse'!$N17:$N132,'Detaillierte Ergebnisse'!$C$2:$C$117, $A39) -> 0.24439776 | G39: =AVERAGEIFS('Detaillierte Ergebnisse'!$O$2:$O$117,'Detaillierte Ergebnisse'!$C$2:$C$117, $A39) -> 0.57049006 | H39: =AVERAGEIFS('Detaillierte Ergebnisse'!$P$2:$P$117,'Detaillierte Ergebnisse'!$C$2:$C$117, $A39) -> 0.15400507 | I39: =AVERAGEIFS('Detaillierte Ergebnisse'!$Q$2:$Q$117,'Detaillierte Ergebnisse'!$C$2:$C$117, $A39) -> 0.15969173 | J39: =AVERAGEIFS('Detaillierte Ergebnisse'!$R$2:$R$117,'Detaillierte Ergebnisse'!$C$2:$C$117, $A39) -> 0.14658083 | K39: =AVERAGEIFS('Detaillierte Ergebnisse'!$S$2:$S$117,'Detaillierte Ergebnisse'!$C$2:$C$117, $A39) -> 0.31818182 | L39: =AVERAGEIFS('Detaillierte Ergebnisse'!$T$2:$T$117,'Detaillierte Ergebnisse'!$C$2:$C$117, $A39) -> 0.36363636 | M39: =AVERAGEIFS('Detaillierte Ergebnisse'!$U$2:$U$117,'Detaillierte Ergebnisse'!$C$2:$C$117, $A39) -> 20.456558 | N39: =AVERAGEIFS('Detaillierte Ergebnisse'!$V$2:$V$117,'Detaillierte Ergebnisse'!$C$2:$C$117, $A39) -> 2211.4091 | O39: =AVERAGEIFS('Detaillierte Ergebnisse'!$W$2:$W$117,'Detaillierte Ergebnisse'!$C$2:$C$117, $A39) -> 234.86364 | P39: =AVERAGEIFS('Detaillierte Ergebnisse'!$X$2:$X$117,'Detaillierte Ergebnisse'!$C$2:$C$117, $A39) -> 2446.2727 | Q39: =AVERAGEIFS('Detaillierte Ergebnisse'!$Y$2:$Y$117,'Detaillierte Ergebnisse'!$C$2:$C$117, $A39) -> 0
